Workbook
Name UPDATE: 'Data Sheet'!$E$1

Sheet Cover Page
B2: Discounted Cash Flow (DCF) Valuation
B7: ='Data Sheet'!B1 -> HINDUSTAN UNILEVER LTD
E14: Prepared By:
E16: Harsh Sharma
D17: CFA Level I Passed
D18: Bachelor of Commerce (Honours)
D19: Accounting & Finance
D20: Panjab University
C22: Financial Modeling | Equity Research | Valuation

Sheet Assumptions and Notes
B2: =IFERROR('Data Sheet'!B1& " - DCF Valuation",0) -> HINDUSTAN UNILEVER LTD - DCF Valuation
B3: Valuation Date: June 2026
B5: A. COMPANY OVERVIEW
B7: HUL is India's largest FMCG company with presence in Home Care, Beauty & Personal Care, and Foods & Refreshment. Revenue: ₹64,468 Cr (FY26) | EBITDA Margin: 23.3% | ROIC: 24.5%
B10: B. REVENUE GROWTH ASSUMPTIONS
B12: FY27E: 10.7% - | C12: Rural recovery + low base (FY26 actual only 5.12%) + volume acceleration
B13: FY28E: 5.6% - | C13: Normalizing toward historical average of 5-8%
B14: FY29E: 5.3% - | C14: Stable FMCG market growth
B15: FY30E: 5.0% - | C15: Converging to long-run India consumption growth
B16: FY31E: 4.8% - | C16: Mature phase; approaching terminal growth
B18: Basis: | C18: HUL 8-year historical revenue CAGR = 7.7%
C19: Management commentary: Q4 FY26 earnings call
B21: C. EBITDA MARGIN ASSUMPTIONS
B23: Base FY26: | C23: 23.3% (actual)
B24: Forecast: | C24: Stable at 23-25% — HUL has maintained this range for 8+ consecutive years. No significant expansion assumed as premiumization gains are offset by rising raw material costs (palm oil, crude derivatives).
B28: D. WACC ASSUMPTIONS
B30: Risk Free Rate: | D30: =WACC!J22 -> 0.0684 | E30: (10-year G-Sec yield, June 2026)
B31: Equity Risk Premium: | D31: =WACC!J23 -> 0.0514 | E31: (20-year geometric mean of Nifty 50 returns less risk-free rate)
B32: Beta: | D32: ='Beta - Regression'!J12 -> 0.67580018 | E32: (Blume Adjusted Beta — Raw Beta × 0.75 + Market Beta × 0.25; 2-year weekly regression vs Nifty 50; 105 observations)
B34: Tax Rate: | D34: 0.25 | E34: (India marginal corporate rate)
B35: Peer Comps Used for Beta: ITC, Varun Beverages, Britannia
B37: E. TERMINAL VALUE ASSUMPTIONS
B39: Terminal Growth Rate: | D39: =DCF!E15 -> 0.04
B40: Basis: | C40: 4% conservative long-run growth rate; below India's real GDP growth (~7%) to account for long-run mean reversion and competitive intensity in mature FMCG market. Standard Damodaran convention followed — terminal growth cannot exceed country's long-run GDP growth.
B45: F. KEY MODEL LIMITATIONS
B47: 1. Model uses 5-year explicit forecast - HUL's brand moat and distribution may justify longer horizon.
B48: 2. Rural recovery timing uncertain - key upside risk.
B49: 3. Crude oil & palm oil prices affect RM costs - not explicitly modeled
B50: 4. Peer set limited to 3 Indian FMCG companies
B52: G. VALUATION SUMMARY
B54: DCF Intrinsic Value: | D54: =DCF!E37 -> 638.10551 | E54: per share
B55: Current Market Price: | D55: =DCF!E39 -> 2160 | E55: per share
B56: Premium to IV: | D56: =DCF!E40 -> 2.3850201
B57: Rating: | D57: SELL / OVERPRICED
B59: Stock trades at 239% premium to our intrinsic value estimate. However, HUL's quality premium — 24%+ ROIC, net cash balance sheet, and dominant distribution network — partially justifies premium. Recommend SELL for value investors, HOLD for quality-focused long-term investors.
B63: Sources: | C63: BSE Annual Reports, Screener.in, Damodaran Online (ERP), NSE (price data), Yahoo Finance

Sheet DCF>

Sheet DCF
B2: Calculation of PV of FCFF | G2: ='Intrinsic Growth'!K2 -> 46090 | H2: =G2+365 -> 46455 | I2: =H2+366 -> 46821 | J2: =I2+365 -> 47186 | K2: =J2+365 -> 47551 | L2: =K2+365 -> 47916
B4: EBIT | G4: =HistoricalFS!K24 -> 13706 | H4: =IFERROR(G4*(1+$E$14),0) -> 13901.73 | I4: =IFERROR(H4*(1+$E$14),0) -> 14100.256 | J4: =IFERROR(I4*(1+$E$14),0) -> 14301.616 | K4: =IFERROR(J4*(1+$E$14),0) -> 14505.852 | L4: =IFERROR(K4*(1+$E$14),0) -> 14713.005
B5: Tax Rate | G5: 0.25 | H5: =G5 -> 0.25 | I5: =H5 -> 0.25 | J5: =I5 -> 0.25 | K5: =J5 -> 0.25 | L5: =K5 -> 0.25
B6: EBIT(1-Tax) | G6: =G4*(1-G5) -> 10279.5 | H6: =H4*(1-H5) -> 10426.298 | I6: =I4*(1-I5) -> 10575.192 | J6: =J4*(1-J5) -> 10726.212 | K6: =K4*(1-K5) -> 10879.389 | L6: =L4*(1-L5) -> 11034.754
B7: Less: Reinvestment Rate | G7: ='Intrinsic Growth'!$K$54 -> 0.13171847 | H7: =G7-(($G$7-$L$7)/5) -> 0.1171285 | I7: =H7-(($G$7-$L$7)/5) -> 0.10253853 | J7: =I7-(($G$7-$L$7)/5) -> 0.087948559 | K7: =J7-(($G$7-$L$7)/5) -> 0.073358588 | L7: ='Intrinsic Growth'!K57 -> 0.058768618
B8: Free Cash Flow to Firm (FCFF) | G8: =G6*(1-G7) -> 8925.5 | H8: =H6*(1-H7) -> 9205.0811 | I8: =I6*(1-I7) -> 9490.8272 | J8: =J6*(1-J7) -> 9782.8573 | K8: =K6*(1-K7) -> 10081.293 | L8: =L6*(1-L7) -> 10386.257
B9: Mid Year Convention | G9: - | H9: 0.5 | I9: =H9+1 -> 1.5 | J9: =I9+1 -> 2.5 | K9: =J9+1 -> 3.5 | L9: =K9+1 -> 4.5
B10: Discounting Factor | G10: - | H10: =1/(1+$E$16)^H9 -> 0.95205372 | I10: =1/(1+$E$16)^I9 -> 0.86294748 | J10: =1/(1+$E$16)^J9 -> 0.78218102 | K10: =1/(1+$E$16)^K9 -> 0.7089738 | L10: =1/(1+$E$16)^L9 -> 0.64261831
B12: PV of FCFF | G12: - | H12: =H8*H10 -> 8763.7317 | I12: =I8*I10 -> 8190.0854 | J12: =J8*J10 -> 7651.9653 | K12: =K8*K10 -> 7147.3723 | L12: =L8*L10 -> 6674.3986
B14: Expected Growth | E14: ='Intrinsic Growth'!K67 -> 0.014280629
B15: Terminal Growth Rate | E15: 0.04
B16: WACC | E16: =WACC!J43 -> 0.10325801
B18: Calculation of Terminal Value | G18: Sensitivity Analysis
G19: =E30 -> 148158.71 | H19: 0.095 | I19: 0.1 | J19: 0.1033 | K19: 0.1075 | L19: 0.1125
B20: FCFF (n+1) | E20: =L8*(1+E15) -> 10801.707 | G20: 0.04 | H20: 164634.36 | I20: 154117.13 | J20: 148085.92 | K20: 141262.73 | L20: 134170.65
B21: WACC | E21: =E16 -> 0.10325801 | G21: 0.045 | H21: 177255.04 | I21: 164634.36 | J21: 157490.58 | K21: 149489.55 | L21: 141262.73
B22: Terminal Growth Rate | E22: =E15 -> 0.04 | G22: 0.05 | H22: 192680.32 | I22: 177255.04 | J22: 168659.72 | K22: 159147.11 | L22: 149489.55
G23: 0.055 | H23: 211961.92 | I23: 192680.32 | J23: 182141.31 | K23: 170644.21 | L23: 159147.11
B24: Terminal Value | E24: =E20/(E21-E22) -> 170756.34 | G24: 0.06 | H24: 236752.54 | I24: 211961.92 | J24: 198736.44 | K24: 184561.75 | L24: 170644.21
B26: Calculation of Equity Value Per Share | H26: Sensitivity values represent Value of Operating Assets (₹ Crores). Equity Value per Share ranges from ₹579 (Bear) to ₹1015 (Bull).
B28: PV of FCFF | E28: =SUM(H12:L12) -> 38427.553
B29: PV of Terminal Value | E29: =E24*L10 -> 109731.15
B30: Value of Operating Assets | E30: =SUM(E28:E29) -> 148158.71
B32: Add: Cash | E32: ='Data Sheet'!K69 -> 3248
B33: Less: Debt | E33: =SUM('Raw FS'!N7:N9) -> 1478
B34: Value of Equity | E34: =E30+E32-E33 -> 149928.71
B35: No. of Shares | E35: ='Data Sheet'!B6 -> 234.95912
B37: Equity Value per Share | E37: =E34/E35 -> 638.10551
B39: Share Price | E39: 2160
B40: Discount/Premium | E40: =E39/E37-1 -> 2.3850201 | F40: (Market trades at 239% premium to IV)
F41: Positive = Premium (Market > IV). Negative = Discount (Market < IV)

Sheet WACC
B2: ="Weighted Average Cost of Capital - " &'Data Sheet'!B1 -> Weighted Average Cost of Capital - HINDUSTAN UNILEVER LTD
B4: All Figures are in INR stated otherwise
B6: Peer Comps
G7: Debt/ | H7: Debt/ | I7: Levered | J7: Unlevered
B8: Name of the Comp | C8: Country | D8: Total Debt | E8: Total Equity | F8: Tax Rate 1 | G8: Equity | H8: Capital | I8: Beta 2 | J8: Beta 3
B10: Hind. Unilever | C10: India | D10: ='Beta - Comps'!F3 -> 1478 | E10: ='Beta - Comps'!E3 -> 508569 | F10: 0.25 | G10: =D10/E10 -> 0.0029061937 | H10: =D10/(D10+E10) -> 0.0028977722 | I10: ='Beta - Regression'!J12 -> 0.67580018 | J10: =I10/(1+(1-F10)*G10) -> 0.67433038
B11: ITC | C11: India | D11: ='Beta - Comps'!F4 -> 2399.06 | E11: ='Beta - Comps'!E4 -> 363605.09 | F11: 0.25 | G11: =D11/E11 -> 0.0065979824 | H11: =D11/(D11+E11) -> 0.0065547344 | I11: ='Beta - Regression'!X12 -> 0.69249061 | J11: =I11/(1+(1-F11)*G11) -> 0.68908071
B12: Varun Beverages | C12: India | D12: ='Beta - Comps'!F5 -> 2508.18 | E12: ='Beta - Comps'!E5 -> 170619.9 | F12: 0.25 | G12: =D12/E12 -> 0.014700395 | H12: =D12/(D12+E12) -> 0.014487425 | I12: ='Beta - Regression'!AL12 -> 1.1299094 | J12: =I12/(1+(1-F12)*G12) -> 1.1175876
B13: Britannia Inds. | C13: India | D13: ='Beta - Comps'!F6 -> 1380.28 | E13: ='Beta - Comps'!E6 -> 126307.76 | F13: 0.25 | G13: =D13/E13 -> 0.010927911 | H13: =D13/(D13+E13) -> 0.010809783 | I13: ='Beta - Regression'!AZ12 -> 0.64522994 | J13: =I13/(1+(1-F13)*G13) -> 0.63998467
E16: Average | F16: =AVERAGE(F10:F13) -> 0.25 | G16: =AVERAGE(G10:G13) -> 0.0087831207 | H16: =AVERAGE(H10:H13) -> 0.0086874285 | I16: =AVERAGE(I10:I13) -> 0.78585753 | J16: =AVERAGE(J10:J13) -> 0.78024585
E17: Median | F17: =MEDIAN(F10:F13) -> 0.25 | G17: =MEDIAN(G10:G13) -> 0.0087629469 | H17: =MEDIAN(H10:H13) -> 0.0086822587 | I17: =MEDIAN(I10:I13) -> 0.6841454 | J17: =MEDIAN(J10:J13) -> 0.68170554
B20: Cost of Debt | G20: Cost of Equity
B22: Pre Tax Cost of Debt | E22: 0.075 | G22: Risk Free Rate | J22: 0.0684
B23: Tax Rate | E23: =F17 -> 0.25 | G23: Equity Risk Premium | J23: =Rm!G11-WACC!J22 -> 0.0514
B24: Post Tax Cost of Debt | E24: =E22*(1-E23) -> 0.05625 | G24: Levered Beta 4 | J24: =J33 -> 0.68618617
G25: Cost of Equity | J25: =J22+(J23*J24) -> 0.10366997
B28: Capital Structure | G28: Levered Beta
D30: Current | E30: Target | G30: Comps Median Unlevered Beta | J30: =J17 -> 0.68170554
B31: Total Debt | C31: =D10 -> 1478 | D31: =C31/$C$33 -> 0.0028977722 | E31: =H16 -> 0.0086874285 | G31: Target Debt / Equity | J31: =E35 -> 0.0087635613
B32: Market Capitalization | C32: =E10 -> 508569 | D32: =C32/$C$33 -> 0.99710223 | E32: =E33-E31 -> 0.99131257 | G32: Tax Rate | J32: =E23 -> 0.25
B33: Total Capital | C33: =SUM(C32,C31) -> 510047 | D33: =C33/$C$33 -> 1 | E33: =D33 -> 1 | G33: Levered Beta | J33: =J30*(1+(1-J32)*J31) -> 0.68618617
B35: Debt / Equity | D35: =D31/D32 -> 0.0029061937 | E35: =E31/E32 -> 0.0087635613 | G35: Weighted Average Cost of Capital
B37: Notes | G37: Cost of Equity | J37: =J25 -> 0.10366997
B38: 1. Tax Rate considered as Marginal Tax Rate for the country | G38: Equity Weight | J38: =E32 -> 0.99131257
B39: 2. Levered Beta is based on 2 years weekly data
B40: 3. Unlevered Beta = Levered Beta/1+(1-Tax Rate)*Debt/Equity | G40: Cost of Debt | J40: =E24 -> 0.05625
B41: 4. Levered Beta = Unlevered Beta*1+(1-Tax Rate)*Debt/Equity | G41: Debt Weight | J41: =E31 -> 0.0086874285
B42: 5.ERP of 5.14% derived from 20-year geometric mean of Nifty 50 returns (10.68%) less risk-free rate (6.84%), adjusted for India's current market conditions.
G43: WACC | J43: =(J38*J37)+(J40*J41) -> 0.10325801

Sheet Intrinsic Growth
B2: Calculation of ROIC | G2: ='Raw FS'!J$2 -> 44626 | H2: ='Raw FS'!K$2 -> 44992 | I2: ='Raw FS'!L$2 -> 45358 | J2: ='Raw FS'!M$2 -> 45724 | K2: ='Raw FS'!N$2 -> 46090
B4: All Figures are in INR stated otherwise
B6: Current Assets
B7: Inventories | G7: ='Raw FS'!J35 -> 4096 | H7: ='Raw FS'!K35 -> 4251 | I7: ='Raw FS'!L35 -> 4022 | J7: ='Raw FS'!M35 -> 4415 | K7: ='Raw FS'!N35 -> 4789
B8: Trade receivables | G8: ='Raw FS'!J36 -> 2236 | H8: ='Raw FS'!K36 -> 3079 | I8: ='Raw FS'!L36 -> 2997 | J8: ='Raw FS'!M36 -> 3819 | K8: ='Raw FS'!N36 -> 3379
B9: Loans n Advances | G9: ='Raw FS'!J38 -> 170 | H9: ='Raw FS'!K38 -> 188 | I9: ='Raw FS'!L38 -> 172 | J9: ='Raw FS'!M38 -> 619 | K9: ='Raw FS'!N38 -> 1024
B10: Other asset items | G10: ='Raw FS'!J39 -> 3851 | H10: ='Raw FS'!K39 -> 4189 | I10: ='Raw FS'!L39 -> 4345 | J10: ='Raw FS'!M39 -> 4302 | K10: ='Raw FS'!N39 -> 4631
B11: Total Current Assets | G11: =SUM(G7:G10) -> 10353 | H11: =SUM(H7:H10) -> 11707 | I11: =SUM(I7:I10) -> 11536 | J11: =SUM(J7:J10) -> 13155 | K11: =SUM(K7:K10) -> 13823
B13: Current Liabilities
B14: Trade Payables | G14: ='Raw FS'!J12 -> 9068 | H14: ='Raw FS'!K12 -> 9574 | I14: ='Raw FS'!L12 -> 10486 | J14: ='Raw FS'!M12 -> 11315 | K14: ='Raw FS'!N12 -> 13325
B15: Advance from Customers | G15: ='Raw FS'!J13 -> 119 | H15: ='Raw FS'!K13 -> 98 | I15: ='Raw FS'!L13 -> 91 | J15: ='Raw FS'!M13 -> 0 | K15: ='Raw FS'!N13 -> 0
B16: Other liability items | G16: ='Raw FS'!J14 -> 11189 | H16: ='Raw FS'!K14 -> 11664 | I16: ='Raw FS'!L14 -> 15005 | J16: ='Raw FS'!M14 -> 17291 | K16: ='Raw FS'!N14 -> 15927
B17: Total Current Liabilities | G17: =SUM(G14:G16) -> 20376 | H17: =SUM(H14:H16) -> 21336 | I17: =SUM(I14:I16) -> 25582 | J17: =SUM(J14:J16) -> 28606 | K17: =SUM(K14:K16) -> 29252
B19: Net Working Capital | G19: =G11-G17 -> -10023 | H19: =H11-H17 -> -9629 | I19: =I11-I17 -> -14046 | J19: =J11-J17 -> -15451 | K19: =K11-K17 -> -15429
B21: Non Current Assets
B22: Land | G22: ='Raw FS'!J18 -> 477 | H22: ='Raw FS'!K18 -> 609 | I22: ='Raw FS'!L18 -> 633 | J22: ='Raw FS'!M18 -> 628 | K22: ='Raw FS'!N18 -> 636
B23: Building | G23: ='Raw FS'!J19 -> 2788 | H23: ='Raw FS'!K19 -> 3101 | I23: ='Raw FS'!L19 -> 3590 | J23: ='Raw FS'!M19 -> 3833 | K23: ='Raw FS'!N19 -> 4067
B24: Plant Machinery | G24: ='Raw FS'!J20 -> 6566 | H24: ='Raw FS'!K20 -> 7612 | I24: ='Raw FS'!L20 -> 8946 | J24: ='Raw FS'!M20 -> 9900 | K24: ='Raw FS'!N20 -> 9296
B25: Equipments | G25: ='Raw FS'!J21 -> 181 | H25: ='Raw FS'!K21 -> 185 | I25: ='Raw FS'!L21 -> 206 | J25: ='Raw FS'!M21 -> 245 | K25: ='Raw FS'!N21 -> 286
B26: Furniture n fittings | G26: ='Raw FS'!J22 -> 152 | H26: ='Raw FS'!K22 -> 161 | I26: ='Raw FS'!L22 -> 165 | J26: ='Raw FS'!M22 -> 174 | K26: ='Raw FS'!N22 -> 220
B27: Railway Sidings | G27: ='Raw FS'!J23 -> 0 | H27: ='Raw FS'!K23 -> 0 | I27: ='Raw FS'!L23 -> 0 | J27: ='Raw FS'!M23 -> 0 | K27: ='Raw FS'!N23 -> 0
B28: Vehicles | G28: ='Raw FS'!J24 -> 0 | H28: ='Raw FS'!K24 -> 33 | I28: ='Raw FS'!L24 -> 39 | J28: ='Raw FS'!M24 -> 102 | K28: ='Raw FS'!N24 -> 103
B29: Intangible Assets | G29: ='Raw FS'!J25 -> 45262 | H29: ='Raw FS'!K25 -> 45692 | I29: ='Raw FS'!L25 -> 45692 | J29: ='Raw FS'!M25 -> 45692 | K29: ='Raw FS'!N25 -> 49195
B30: Other fixed assets | G30: ='Raw FS'!J26 -> 152 | H30: ='Raw FS'!K26 -> 171 | I30: ='Raw FS'!L26 -> 180 | J30: ='Raw FS'!M26 -> 190 | K30: ='Raw FS'!N26 -> 210
B31: Gross Block | G31: =SUM(G22:G30) -> 55578 | H31: =SUM(H22:H30) -> 57564 | I31: =SUM(I22:I30) -> 59451 | J31: =SUM(J22:J30) -> 60764 | K31: =SUM(K22:K30) -> 64013
B32: Accumulated Depriciation | G32: ='Raw FS'!J28 -> 4105 | H32: ='Raw FS'!K28 -> 4886 | I32: ='Raw FS'!L28 -> 5707 | J32: ='Raw FS'!M28 -> 6429 | K32: ='Raw FS'!N28 -> 6585
B33: Net Non Current Assets | G33: =G31-G32 -> 51473 | H33: =H31-H32 -> 52678 | I33: =I31-I32 -> 53744 | J33: =J31-J32 -> 54335 | K33: =K31-K32 -> 57428
B35: Invested Capital | G35: =G19+G33 -> 41450 | H35: =H19+H33 -> 43049 | I35: =I19+I33 -> 39698 | J35: =J19+J33 -> 38884 | K35: =K19+K33 -> 41999
B36: EBIT | G36: =IFERROR(HistoricalFS!G24,0) -> 11766 | H36: =IFERROR(HistoricalFS!H24,0) -> 13010 | I36: =IFERROR(HistoricalFS!I24,0) -> 13443 | J36: =IFERROR(HistoricalFS!J24,0) -> 13445 | K36: =IFERROR(HistoricalFS!K24,0) -> 13706
B37: Marginal Tax Rate | G37: 0.25 | H37: 0.25 | I37: 0.25 | J37: 0.25 | K37: 0.25
B38: EBIT(1-T) | G38: =G36*(1-G37) -> 8824.5 | H38: =H36*(1-H37) -> 9757.5 | I38: =I36*(1-I37) -> 10082.25 | J38: =J36*(1-J37) -> 10083.75 | K38: =K36*(1-K37) -> 10279.5
B40: ROIC | G40: =G38/G35 -> 0.21289505 | H40: =H38/H35 -> 0.22666032 | I40: =I38/I35 -> 0.25397375 | J40: =J38/J35 -> 0.25932903 | K40: =K38/K35 -> 0.24475583
B43: Calculation of Reinvestment Rate | G43: =G2 -> 44626 | H43: =H2 -> 44992 | I43: =I2 -> 45358 | J43: =J2 -> 45724 | K43: =K2 -> 46090
B45: Net Capex | G45: =-SUM('Raw FS'!J58:J59) -> 1053 | H45: =-SUM('Raw FS'!K58:K59) -> 1011 | I45: =-SUM('Raw FS'!L58:L59) -> 1457 | J45: =-SUM('Raw FS'!M58:M59) -> 1262 | K45: =-SUM('Raw FS'!N58:N59) -> 1332
B46: Change in Working Capital | H46: =H19-G19 -> 394 | I46: =I19-H19 -> -4417 | J46: =J19-I19 -> -1405 | K46: =K19-J19 -> 22
B48: EBIT | G48: =G36 -> 11766 | H48: =H36 -> 13010 | I48: =I36 -> 13443 | J48: =J36 -> 13445 | K48: =K36 -> 13706
B49: Marginal Tax Rate | G49: =G37 -> 0.25 | H49: =H37 -> 0.25 | I49: =I37 -> 0.25 | J49: =J37 -> 0.25 | K49: =K37 -> 0.25
B50: EBIT(1-T) | G50: =G38 -> 8824.5 | H50: =H38 -> 9757.5 | I50: =I38 -> 10082.25 | J50: =J38 -> 10083.75 | K50: =K38 -> 10279.5
B52: Reinvestment | H52: =SUM(H45:H46) -> 1405 | I52: =SUM(I45:I46) -> -2960 | J52: =SUM(J45:J46) -> -143 | K52: =SUM(K45:K46) -> 1354
B54: Reinvestment Rate | H54: =H52/H50 -> 0.1439918 | I54: =I52/I50 -> -0.29358526 | J54: =J52/J50 -> -0.014181232 | K54: =K52/K50 -> 0.13171847
J56: 4 Year Average | K56: =AVERAGE(H54:K54) -> -0.0080140559
J57: 4 Year Median | K57: =MEDIAN(H54:K54) -> 0.058768618
B59: Calculation of Growth Rate | G59: =G43 -> 44626 | H59: =H43 -> 44992 | I59: =I43 -> 45358 | J59: =J43 -> 45724 | K59: =K43 -> 46090
B61: Reinvestment Rate | H61: =H54 -> 0.1439918 | I61: =I54 -> -0.29358526 | J61: =J54 -> -0.014181232 | K61: =K54 -> 0.13171847
B62: ROIC | H62: =H40 -> 0.22666032 | I62: =I40 -> 0.25397375 | J62: =J40 -> 0.25932903 | K62: =K40 -> 0.24475583
B64: Intrinsic Growth | H64: =H61*H62 -> 0.032637227 | I64: =I61*I62 -> -0.07456295 | J64: =J61*J62 -> -0.0036776052 | K64: =K61*K62 -> 0.032238863
J66: 4 Year Average | K66: =AVERAGE(H64:K64) -> -0.0033411163
J67: 4 Year Median | K67: =MEDIAN(H64:K64) -> 0.014280629

Sheet Football Field
B3: Football Field Analysis - Valuation Summary | L3: Footlball Field Analysis - Data
M4: OpenLow | N4: Low | O4: OpenHigh | P4: High
L5: Comps | M5: 2021.3 | N5: 2021.3 | O5: 3434.9 | P5: 3434.9
L6: DCF Bear | M6: 578.6 | N6: 578.6 | O6: 733.8 | P6: 733.8
L7: DCF Base | M7: 637.8 | N7: 637.8 | O7: 853.4 | P7: 853.4
L8: DCF Bull | M8: 708.2 | N8: 708.2 | O8: 1015.2 | P8: 1015.2
L9: 52W H/L | M9: 2022.5 | N9: 2022.5 | O9: 2750 | P9: 2750

Sheet Comps Val
B2: Amount in Crores
B3: Comparable Company Valuation
C5: Market Data | K5: Financials | O5: Valuation
B6: Company | C6: Ticker | D6: Share Price | E6: Shares Outstanding | F6: Equity Value | G6: Net Debt | H6: Enterprise Value | K6: Revenue | L6: EBITDA | M6: Net Income | O6: EV/Revenue | P6: EV/EBITDA | Q6: P/E
B9: ='Comps Data'!C4 -> Hind. Unilever | C9: HINDUNILVR | D9: ='Comps Data'!D4 -> 2157.8 | E9: ='Comps Data'!E4 -> 234.96 | F9: =E9*D9 -> 506996.69 | G9: ='Comps Data'!I4 -> -1770 | H9: =F9+G9 -> 505226.69 | K9: ='Comps Data'!K4 -> 64468 | L9: ='Comps Data'!L4 -> 15472.32 | M9: ='Comps Data'!M4 -> 15059 | O9: =$H9/K9 -> 7.83686 | P9: =$H9/L9 -> 32.653583 | Q9: =F9/M9 -> 33.667354
B10: ='Comps Data'!C5 -> ITC | C10: ITC | D10: ='Comps Data'!D5 -> 290.35 | E10: ='Comps Data'!E5 -> 1252.95 | F10: =E10*D10 -> 363794.03 | G10: ='Comps Data'!I5 -> -609.73 | H10: =F10+G10 -> 363184.3 | K10: ='Comps Data'!K5 -> 78868.4 | L10: ='Comps Data'!L5 -> 29969.992 | M10: ='Comps Data'!M5 -> 21018.15 | O10: =$H10/K10 -> 4.6049407 | P10: =$H10/L10 -> 12.118265 | Q10: =F10/M10 -> 17.308566
B11: ='Comps Data'!C6 -> Nestle India | C11: NESTLEIND | D11: ='Comps Data'!D6 -> 1382.6 | E11: ='Comps Data'!E6 -> 192.83 | F11: =E11*D11 -> 266606.76 | G11: ='Comps Data'!I6 -> -896.71 | H11: =F11+G11 -> 265710.05 | K11: ='Comps Data'!K6 -> 23154.6 | L11: ='Comps Data'!L6 -> 5325.558 | M11: ='Comps Data'!M6 -> 3544.6 | O11: =$H11/K11 -> 11.475476 | P11: =$H11/L11 -> 49.893372 | Q11: =F11/M11 -> 75.214907
B12: ='Comps Data'!C7 -> Varun Beverages | C12: VBL | D12: ='Comps Data'!D7 -> 506.7 | E12: ='Comps Data'!E7 -> 338.23 | F12: =E12*D12 -> 171381.14 | G12: ='Comps Data'!I7 -> 509.69 | H12: =F12+G12 -> 171890.83 | K12: ='Comps Data'!K7 -> 22692.63 | L12: ='Comps Data'!L7 -> 5673.1575 | M12: ='Comps Data'!M7 -> 3209.4 | O12: =$H12/K12 -> 7.5747426 | P12: =$H12/L12 -> 30.29897 | Q12: =F12/M12 -> 53.399745
B13: ='Comps Data'!C8 -> Britannia Inds. | C13: BRITANNIA | D13: ='Comps Data'!D8 -> 5262.5 | E13: ='Comps Data'!E8 -> 24.09 | F13: =E13*D13 -> 126773.62 | G13: ='Comps Data'!I8 -> 1027.84 | H13: =F13+G13 -> 127801.46 | K13: ='Comps Data'!K8 -> 19151.59 | L13: ='Comps Data'!L8 -> 3830.318 | M13: ='Comps Data'!M8 -> 2537.01 | O13: =$H13/K13 -> 6.6731517 | P13: =$H13/L13 -> 33.365758 | Q13: =F13/M13 -> 49.969699
B14: ='Comps Data'!C9 -> Tata Consumer | C14: TATACONSUM | D14: ='Comps Data'!D9 -> 1098.1 | E14: ='Comps Data'!E9 -> 98.96 | F14: =E14*D14 -> 108667.98 | G14: ='Comps Data'!I9 -> -600.98 | H14: =F14+G14 -> 108067 | K14: ='Comps Data'!K9 -> 20290.43 | L14: ='Comps Data'!L9 -> 2840.6602 | M14: ='Comps Data'!M9 -> 1546.8 | O14: =$H14/K14 -> 5.3260082 | P14: =$H14/L14 -> 38.042916 | Q14: =F14/M14 -> 70.253411
B15: ='Comps Data'!C10 -> Marico | C15: MARICO | D15: ='Comps Data'!D10 -> 819.45 | E15: ='Comps Data'!E10 -> 129.84 | F15: =E15*D15 -> 106397.39 | G15: ='Comps Data'!I10 -> 64 | H15: =F15+G15 -> 106461.39 | K15: ='Comps Data'!K10 -> 13611 | L15: ='Comps Data'!L10 -> 2586.09 | M15: ='Comps Data'!M10 -> 1813 | O15: =$H15/K15 -> 7.8217168 | P15: =$H15/L15 -> 41.166931 | Q15: =F15/M15 -> 58.685818
B16: ='Comps Data'!C11 -> Godrej Consumer | C16: GODREJCP | D16: ='Comps Data'!D11 -> 1020.5 | E16: ='Comps Data'!E11 -> 102.32 | F16: =E16*D16 -> 104417.56 | G16: ='Comps Data'!I11 -> 3410.4 | H16: =F16+G16 -> 107827.96 | K16: ='Comps Data'!K11 -> 15177.9 | L16: ='Comps Data'!L11 -> 3490.917 | M16: ='Comps Data'!M11 -> 1861.47 | O16: =$H16/K16 -> 7.104274 | P16: =$H16/L16 -> 30.888148 | Q16: =F16/M16 -> 56.094141
B17: ='Comps Data'!C12 -> United Spirits | C17: UNITDSPR | D17: ='Comps Data'!D12 -> 1359.1 | E17: ='Comps Data'!E12 -> 72.74 | F17: =E17*D17 -> 98860.934 | G17: ='Comps Data'!I12 -> -1564 | H17: =F17+G17 -> 97296.934 | K17: ='Comps Data'!K12 -> 12467 | L17: ='Comps Data'!L12 -> 2742.74 | M17: ='Comps Data'!M12 -> 1838 | O17: =$H17/K17 -> 7.8043582 | P17: =$H17/L17 -> 35.474356 | Q17: =F17/M17 -> 53.787233
B18: ='Comps Data'!C13 -> Dabur India | C18: DABUR | D18: ='Comps Data'!D13 -> 424.1 | E18: ='Comps Data'!E13 -> 177.4 | F18: =E18*D18 -> 75235.34 | G18: ='Comps Data'!I13 -> 725.25 | H18: =F18+G18 -> 75960.59 | K18: ='Comps Data'!K13 -> 13192.57 | L18: ='Comps Data'!L13 -> 3034.2911 | M18: ='Comps Data'!M13 -> 1868.69 | O18: =$H18/K18 -> 5.7578311 | P18: =$H18/L18 -> 25.034048 | Q18: =F18/M18 -> 40.261006
B20: High | O20: =MAX(O9:O18) -> 11.475476 | P20: =MAX(P9:P18) -> 49.893372 | Q20: =MAX(Q9:Q18) -> 75.214907
B21: 75th Percentile | O21: =QUARTILE(O9:O18,3) -> 7.8173772 | P21: =QUARTILE(P9:P18,3) -> 37.400776 | Q21: =QUARTILE(Q9:Q18,3) -> 58.037899
B22: Average | O22: =AVERAGE(O9:O18) -> 7.1979359 | P22: =AVERAGE(P9:P18) -> 32.893635 | Q22: =AVERAGE(Q9:Q18) -> 50.864188
B23: Median | O23: =MEDIAN(O9:O18) -> 7.3395083 | P23: =MEDIAN(P9:P18) -> 33.009671 | Q23: =MEDIAN(Q9:Q18) -> 53.593489
B24: 25th Percentile | O24: =QUARTILE(O9:O18,1) -> 5.9866613 | P24: =QUARTILE(P9:P18,1) -> 30.446265 | Q24: =QUARTILE(Q9:Q18,1) -> 42.688179
B25: Low | O25: =MIN(O9:O18) -> 4.6049407 | P25: =MIN(P9:P18) -> 12.118265 | Q25: =MIN(Q9:Q18) -> 17.308566
B27: HINDUSTAN UNILEVER LTD Comparable Valuation | O27: EV/Revenue | P27: EV/EBITDA | Q27: P/E
B29: Implied Enterprise Value | O29: =O$23*K9 -> 473163.42 | P29: =P$23*L9 -> 510736.19 | Q29: =Q30+Q31 -> 805294.35
B30: Net Debt | O30: =$G$9 -> -1770 | P30: =$G$9 -> -1770 | Q30: =$G$9 -> -1770
B31: Implied Market Value | O31: =O29-O30 -> 474933.42 | P31: =P29-P30 -> 512506.19 | Q31: =Q23*M9 -> 807064.35
B32: Shares Outstanding | O32: =$E$9 -> 234.96 | P32: =$E$9 -> 234.96 | Q32: =$E$9 -> 234.96
B34: Implied Value per Share | O34: =O31/O32 -> 2021.3373 | P34: =P31/P32 -> 2181.2487 | Q34: =Q31/Q32 -> 3434.901
B36: Source: The Valuation School, Screener.in
O37: =IF(O34>$D$9,"Undervalued","Overvalued") -> Overvalued | P37: =IF(P34>$D$9,"Undervalued","Overvalued") -> Undervalued | Q37: =IF(Q34>$D$9,"Undervalued","Overvalued") -> Undervalued

Sheet Data>

Sheet Beta - Regression
B2: Regression Beta - 2 Years weekly
B4: ='Data Sheet'!B1&" Weekly Returns" -> HINDUSTAN UNILEVER LTD Weekly Returns | F4: Nifty Returns | I4: Beta Drifting | S4: ITC Weekly Returns | W4: Beta Drifting | AG4: Varun Beverages Ltd Weekly Returns | AK4: Beta Drifting | AU4: Britannia Inds. Ltd Weekly Returns | AY4: Beta Drifting
B6: Date | C6: Closing Price | D6: Return | F6: Closing Price | G6: Return | I6: Levered Raw Data | J6: =M8 -> 0.56773358 | L6: Beta 1 | M6: =SLOPE(D8:D112,G8:G112) -> 0.56773358 | S6: Date | T6: Closing Price | U6: Returns | W6: Levered Raw Data | X6: =AA8 -> 0.58998748 | Z6: Beta 1 | AA6: =SLOPE(U8:U112,G8:G112) -> 0.58998748 | AG6: Date | AH6: Closing Price | AI6: Return | AK6: Levered Raw Data | AL6: =AO8 -> 1.1732125 | AN6: Beta 1 | AO6: =SLOPE(AI8:AI112,G8:G112) -> 1.1732125 | AU6: Date | AV6: Adj Close | AW6: Return | AY6: Levered Raw Data | AZ6: =BC8 -> 0.52697325 | BB6: Beta 1 | BC6: =SLOPE(AW8:AW112,G8:G112) -> 0.52697325
B7: 45467 | C7: 2376.13 | F7: 24010.6 | I7: Raw Beta Weight | J7: 0.75 | L7: Beta 2 | M7: =_xlfn.COVARIANCE.S(D8:D112,G8:G112)/_xlfn.VAR.S(G8:G112) -> 0.56773358 | S7: 45467 | T7: 377.11 | W7: Raw Beta Weight | X7: 0.75 | Z7: Beta 2 | AA7: =_xlfn.COVARIANCE.S(U8:U112,G8:G112)/_xlfn.VAR.S(G8:G112) -> 0.58998748 | AG7: 45467 | AH7: 647.97 | AK7: Raw Beta Weight | AL7: 0.75 | AN7: Beta 2 | AO7: =_xlfn.COVARIANCE.S(AI8:AI112,G8:G112)/_xlfn.VAR.S(G8:G112) -> 1.1732125 | AU7: 45467 | AV7: 5335.28 | AY7: Raw Beta Weight | AZ7: 0.75 | BB7: Beta 2 | BC7: =_xlfn.COVARIANCE.S(AW8:AW112,G8:G112)/_xlfn.VAR.S(G8:G112) -> 0.52697325
B8: 45474 | C8: 2447.18 | D8: =C8/C7-1 -> 0.029901563 | F8: 24323.85 | G8: =F8/F7-1 -> 0.013046321 | L8: Beta 3 | M8: =J31 -> 0.56773358 | S8: 45474 | T8: 384.87 | U8: =T8/T7-1 -> 0.02057755 | Z8: Beta 3 | AA8: =X31 -> 0.58998748 | AG8: 45474 | AH8: 641.87 | AI8: =AH8/AH7-1 -> -0.0094140161 | AN8: Beta 3 | AO8: =AL31 -> 1.1732125 | AU8: 45474 | AV8: 5404.7 | AW8: =AV8/AV7-1 -> 0.013011501 | BB8: Beta 3 | BC8: =AZ31 -> 0.52697325
B9: 45481 | C9: 2519.48 | D9: =C9/C8-1 -> 0.02954421 | F9: 24502.15 | G9: =F9/F8-1 -> 0.0073302541 | I9: Market Beta | J9: 1 | S9: 45481 | T9: 407.41 | U9: =T9/T8-1 -> 0.05856523 | W9: Market Beta | X9: 1 | AG9: 45481 | AH9: 630.08 | AI9: =AH9/AH8-1 -> -0.018368205 | AK9: Market Beta | AL9: 1 | AU9: 45481 | AV9: 5638.8 | AW9: =AV9/AV8-1 -> 0.043314152 | AY9: Market Beta | AZ9: 1
B10: 45488 | C10: 2620.12 | D10: =C10/C9-1 -> 0.039944751 | F10: 24530.9 | G10: =F10/F9-1 -> 0.0011733664 | I10: Market Beta Weight | J10: 0.25 | S10: 45488 | T10: 421.17 | U10: =T10/T9-1 -> 0.033774331 | W10: Market Beta Weight | X10: 0.25 | AG10: 45488 | AH10: 620.21 | AI10: =AH10/AH9-1 -> -0.015664678 | AK10: Market Beta Weight | AL10: 0.25 | AU10: 45488 | AV10: 5727.37 | AW10: =AV10/AV9-1 -> 0.015707243 | AY10: Market Beta Weight | AZ10: 0.25
B11: 45495 | C11: 2604.8 | D11: =C11/C10-1 -> -0.0058470604 | F11: 24834.85 | G11: =F11/F10-1 -> 0.012390495 | S11: 45495 | T11: 445.71 | U11: =T11/T10-1 -> 0.058266258 | AG11: 45495 | AH11: 666.72 | AI11: =AH11/AH10-1 -> 0.074990729 | AU11: 45495 | AV11: 5722.35 | AW11: =AV11/AV10-1 -> -0.00087649305
B12: 45502 | C12: 2587.03 | D12: =C12/C11-1 -> -0.0068220209 | F12: 24717.7 | G12: =F12/F11-1 -> -0.0047171616 | I12: Adjusted Beta | J12: =(J6*J7)+(J9*J10) -> 0.67580018 | S12: 45502 | T12: 434.08 | U12: =T12/T11-1 -> -0.0260932 | W12: Adjusted Beta | X12: =(X6*X7)+(X9*X10) -> 0.69249061 | AG12: 45502 | AH12: 625.24 | AI12: =AH12/AH11-1 -> -0.062215023 | AK12: Adjusted Beta | AL12: =(AL6*AL7)+(AL9*AL10) -> 1.1299094 | AU12: 45502 | AV12: 5573.81 | AW12: =AV12/AV11-1 -> -0.025957867 | AY12: Adjusted Beta | AZ12: =(AZ6*AZ7)+(AZ9*AZ10) -> 0.64522994
B13: 45509 | C13: 2639.53 | D13: =C13/C12-1 -> 0.020293541 | F13: 24367.5 | G13: =F13/F12-1 -> -0.014167985 | S13: 45509 | T13: 440.12 | U13: =T13/T12-1 -> 0.013914486 | AG13: 45509 | AH13: 599.89 | AI13: =AH13/AH12-1 -> -0.040544431 | AU13: 45509 | AV13: 5593.24 | AW13: =AV13/AV12-1 -> 0.0034859459
B14: 45516 | C14: 2640.54 | D14: =C14/C13-1 -> 0.00038264388 | F14: 24541.15 | G14: =F14/F13-1 -> 0.0071262953 | I14: SUMMARY OUTPUT | S14: 45516 | T14: 446.11 | U14: =T14/T13-1 -> 0.013609925 | W14: SUMMARY OUTPUT | AG14: 45516 | AH14: 565.87 | AI14: =AH14/AH13-1 -> -0.056710397 | AK14: SUMMARY OUTPUT | AU14: 45516 | AV14: 5655.53 | AW14: =AV14/AV13-1 -> 0.011136658 | AY14: SUMMARY OUTPUT
B15: 45523 | C15: 2705.25 | D15: =C15/C14-1 -> 0.024506351 | F15: 24823.15 | G15: =F15/F14-1 -> 0.011490904 | S15: 45523 | T15: 448.91 | U15: =T15/T14-1 -> 0.0062764789 | AG15: 45523 | AH15: 629.65 | AI15: =AH15/AH14-1 -> 0.1127114 | AU15: 45523 | AV15: 5717.72 | AW15: =AV15/AV14-1 -> 0.010996317
B16: 45530 | C16: 2669.13 | D16: =C16/C15-1 -> -0.013351816 | F16: 25235.9 | G16: =F16/F15-1 -> 0.016627624 | I16: Regression Statistics | S16: 45530 | T16: 445.44 | U16: =T16/T15-1 -> -0.0077298345 | W16: Regression Statistics | AG16: 45530 | AH16: 597.33 | AI16: =AH16/AH15-1 -> -0.051330104 | AK16: Regression Statistics | AU16: 45530 | AV16: 5779.51 | AW16: =AV16/AV15-1 -> 0.010806755 | AY16: Regression Statistics
B17: 45537 | C17: 2727.69 | D17: =C17/C16-1 -> 0.021939733 | F17: 24852.15 | G17: =F17/F16-1 -> -0.015206511 | I17: Multiple R | J17: 0.38095448 | S17: 45537 | T17: 445.27 | U17: =T17/T16-1 -> -0.00038164511 | W17: Multiple R | X17: 0.3953394 | AG17: 45537 | AH17: 594.29 | AI17: =AH17/AH16-1 -> -0.0050893141 | AK17: Multiple R | AL17: 0.48124078 | AU17: 45537 | AV17: 5767.96 | AW17: =AV17/AV16-1 -> -0.0019984393 | AY17: Multiple R | AZ17: 0.33058568
B18: 45544 | C18: 2818 | D18: =C18/C17-1 -> 0.033108601 | F18: 25356.5 | G18: =F18/F17-1 -> 0.020294019 | I18: R Square | J18: 0.14512632 | S18: 45544 | T18: 456.05 | U18: =T18/T17-1 -> 0.02421003 | W18: R Square | X18: 0.15629324 | AG18: 45544 | AH18: 643.39 | AI18: =AH18/AH17-1 -> 0.082619596 | AK18: R Square | AL18: 0.23159269 | AU18: 45544 | AV18: 6053.77 | AW18: =AV18/AV17-1 -> 0.049551315 | AY18: R Square | AZ18: 0.10928689
B19: 45551 | C19: 2860.9 | D19: =C19/C18-1 -> 0.015223563 | F19: 25790.95 | G19: =F19/F18-1 -> 0.017133674 | I19: Adjusted R Square | J19: 0.13682658 | S19: 45551 | T19: 456.54 | U19: =T19/T18-1 -> 0.0010744436 | W19: Adjusted R Square | X19: 0.14810191 | AG19: 45551 | AH19: 651.15 | AI19: =AH19/AH18-1 -> 0.012061114 | AK19: Adjusted R Square | AL19: 0.22413242 | AU19: 45551 | AV19: 6130.21 | AW19: =AV19/AV18-1 -> 0.012626842 | AY19: Adjusted R Square | AZ19: 0.10063919
B20: 45558 | C20: 2850 | D20: =C20/C19-1 -> -0.0038099899 | F20: 26178.95 | G20: =F20/F19-1 -> 0.015044037 | I20: Standard Error | J20: 0.025402507 | S20: 45558 | T20: 463.9 | U20: =T20/T19-1 -> 0.01612126 | W20: Standard Error | X20: 0.025271009 | AG20: 45558 | AH20: 605.48 | AI20: =AH20/AH19-1 -> -0.070137449 | AK20: Standard Error | AL20: 0.039397087 | AU20: 45558 | AV20: 6187.71 | AW20: =AV20/AV19-1 -> 0.0093797765 | AY20: Standard Error | AZ20: 0.027734962
B21: 45565 | C21: 2737.1 | D21: =C21/C20-1 -> -0.039614035 | F21: 25014.6 | G21: =F21/F20-1 -> -0.044476574 | I21: Observations | J21: 105 | S21: 45565 | T21: 446.91 | U21: =T21/T20-1 -> -0.036624272 | W21: Observations | X21: 105 | AG21: 45565 | AH21: 575.98 | AI21: =AH21/AH20-1 -> -0.048721675 | AK21: Observations | AL21: 105 | AU21: 45565 | AV21: 6125.72 | AW21: =AV21/AV20-1 -> -0.010018246 | AY21: Observations | AZ21: 105
B22: 45572 | C22: 2674.12 | D22: =C22/C21-1 -> -0.023009755 | F22: 24964.25 | G22: =F22/F21-1 -> -0.0020128245 | S22: 45572 | T22: 433.29 | U22: =T22/T21-1 -> -0.030475935 | AG22: 45572 | AH22: 589.36 | AI22: =AH22/AH21-1 -> 0.023229973 | AU22: 45572 | AV22: 5901.17 | AW22: =AV22/AV21-1 -> -0.036656915
B23: 45579 | C23: 2610.61 | D23: =C23/C22-1 -> -0.023749869 | F23: 24854.05 | G23: =F23/F22-1 -> -0.0044143125 | I23: ANOVA | S23: 45579 | T23: 431.95 | U23: =T23/T22-1 -> -0.003092617 | W23: ANOVA | AG23: 45579 | AH23: 585.78 | AI23: =AH23/AH22-1 -> -0.0060743858 | AK23: ANOVA | AU23: 45579 | AV23: 5811.05 | AW23: =AV23/AV22-1 -> -0.015271548 | AY23: ANOVA
B24: 45586 | C24: 2428.97 | D24: =C24/C23-1 -> -0.069577608 | F24: 24180.8 | G24: =F24/F23-1 -> -0.027088141 | J24: df | K24: SS | L24: MS | M24: F | N24: Significance F | S24: 45586 | T24: 428.05 | U24: =T24/T23-1 -> -0.0090288228 | X24: df | Y24: SS | Z24: MS | AA24: F | AB24: Significance F | AG24: 45586 | AH24: 608.12 | AI24: =AH24/AH23-1 -> 0.038137185 | AL24: df | AM24: SS | AN24: MS | AO24: F | AP24: Significance F | AU24: 45586 | AV24: 5596.06 | AW24: =AV24/AV23-1 -> -0.036996756 | AZ24: df | BA24: SS | BB24: MS | BC24: F | BD24: Significance F
B25: 45593 | C25: 2438.05 | D25: =C25/C24-1 -> 0.00373821 | F25: 24304.35 | G25: =F25/F24-1 -> 0.0051094257 | I25: Regression | J25: 1 | K25: 0.011283261 | L25: 0.011283261 | M25: 17.485637 | N25: 6.0934746e-05 | S25: 45593 | T25: 435.15 | U25: =T25/T24-1 -> 0.016586847 | W25: Regression | X25: 1 | Y25: 0.012185155 | Z25: 0.012185155 | AA25: 19.080331 | AB25: 2.9944915e-05 | AG25: 45593 | AH25: 605.43 | AI25: =AH25/AH24-1 -> -0.0044234691 | AK25: Regression | AL25: 1 | AM25: 0.048183552 | AN25: 0.048183552 | AO25: 31.043493 | AP25: 2.0289498e-07 | AU25: 45593 | AV25: 5619.41 | AW25: =AV25/AV24-1 -> 0.0041725786 | AY25: Regression | AZ25: 1 | BA25: 0.0097212609 | BB25: 0.0097212609 | BC25: 12.637683 | BD25: 0.00057250387
B26: 45600 | C26: 2409.42 | D26: =C26/C25-1 -> -0.011742991 | F26: 24148.2 | G26: =F26/F25-1 -> -0.0064247758 | I26: Residual | J26: 103 | K26: 0.066464598 | L26: 0.00064528736 | S26: 45600 | T26: 424.28 | U26: =T26/T25-1 -> -0.024979892 | W26: Residual | X26: 103 | Y26: 0.06577826 | Z26: 0.00063862389 | AG26: 45600 | AH26: 588.57 | AI26: =AH26/AH25-1 -> -0.027847976 | AK26: Residual | AL26: 103 | AM26: 0.15986944 | AN26: 0.0015521305 | AU26: 45600 | AV26: 5672.81 | AW26: =AV26/AV25-1 -> 0.009502777 | AY26: Residual | AZ26: 103 | BA26: 0.079230498 | BB26: 0.00076922813
B27: 45607 | C27: 2322.27 | D27: =C27/C26-1 -> -0.036170531 | F27: 23532.7 | G27: =F27/F26-1 -> -0.025488442 | I27: Total | J27: 104 | K27: 0.077747859 | S27: 45607 | T27: 413.54 | U27: =T27/T26-1 -> -0.025313472 | W27: Total | X27: 104 | Y27: 0.077963415 | AG27: 45607 | AH27: 572.75 | AI27: =AH27/AH26-1 -> -0.026878706 | AK27: Total | AL27: 104 | AM27: 0.20805299 | AU27: 45607 | AV27: 4852.01 | AW27: =AV27/AV26-1 -> -0.1446902 | AY27: Total | AZ27: 104 | BA27: 0.088951759
B28: 45614 | C28: 2376.75 | D28: =C28/C27-1 -> 0.023459804 | F28: 23907.25 | G28: =F28/F27-1 -> 0.015916151 | S28: 45614 | T28: 421.26 | U28: =T28/T27-1 -> 0.018668085 | AG28: 45614 | AH28: 613.29 | AI28: =AH28/AH27-1 -> 0.070781318 | AU28: 45614 | AV28: 4785.63 | AW28: =AV28/AV27-1 -> -0.013680928
B29: 45621 | C29: 2426.23 | D29: =C29/C28-1 -> 0.020818344 | F29: 24131.1 | G29: =F29/F28-1 -> 0.0093632685 | J29: Coefficients | K29: Standard Error | L29: t Stat | M29: P-value | N29: Lower 95% | O29: Upper 95% | P29: Lower 95.0% | Q29: Upper 95.0% | S29: 45621 | T29: 423.12 | U29: =T29/T28-1 -> 0.0044153255 | X29: Coefficients | Y29: Standard Error | Z29: t Stat | AA29: P-value | AB29: Lower 95% | AC29: Upper 95% | AD29: Lower 95.0% | AE29: Upper 95.0% | AG29: 45621 | AH29: 618.07 | AI29: =AH29/AH28-1 -> 0.0077940289 | AL29: Coefficients | AM29: Standard Error | AN29: t Stat | AO29: P-value | AP29: Lower 95% | AQ29: Upper 95% | AR29: Lower 95.0% | AS29: Upper 95.0% | AU29: 45621 | AV29: 4877.23 | AW29: =AV29/AV28-1 -> 0.019140636 | AZ29: Coefficients | BA29: Standard Error | BB29: t Stat | BC29: P-value | BD29: Lower 95% | BE29: Upper 95% | BF29: Lower 95.0% | BG29: Upper 95.0%
B30: 45628 | C30: 2414.22 | D30: =C30/C29-1 -> -0.0049500666 | F30: 24677.8 | G30: =F30/F29-1 -> 0.022655411 | I30: Intercept | J30: -0.00056223623 | K30: 0.0024790647 | L30: -0.22679369 | M30: 0.82103368 | N30: -0.0054788764 | O30: 0.004354404 | P30: -0.0054788764 | Q30: 0.004354404 | S30: 45628 | T30: 418.15 | U30: =T30/T29-1 -> -0.011746077 | W30: Intercept | X30: -0.0021752446 | Y30: 0.0024662316 | Z30: -0.88201147 | AA30: 0.37982433 | AB30: -0.0070664334 | AC30: 0.0027159442 | AD30: -0.0070664334 | AE30: 0.0027159442 | AG30: 45628 | AH30: 640.8 | AI30: =AH30/AH29-1 -> 0.03677577 | AK30: Intercept | AL30: -0.0015104429 | AM30: 0.0038448146 | AN30: -0.39285194 | AO30: 0.69524071 | AP30: -0.0091357258 | AQ30: 0.0061148401 | AR30: -0.0091357258 | AS30: 0.0061148401 | AU30: 45628 | AV30: 4807.84 | AW30: =AV30/AV29-1 -> -0.014227338 | AY30: Intercept | AZ30: 0.00021421359 | BA30: 0.0027066922 | BB30: 0.079142206 | BC30: 0.93707307 | BD30: -0.0051538719 | BE30: 0.0055822991 | BF30: -0.0051538719 | BG30: 0.0055822991
B31: 45635 | C31: 2323.15 | D31: =C31/C30-1 -> -0.037722329 | F31: 24768.3 | G31: =F31/F30-1 -> 0.0036672637 | I31: X Variable 1 | J31: 0.56773358 | K31: 0.13577001 | L31: 4.1815831 | M31: 6.0934746e-05 | N31: 0.29846578 | O31: 0.83700137 | P31: 0.29846578 | Q31: 0.83700137 | S31: 45635 | T31: 417.13 | U31: =T31/T30-1 -> -0.002439316 | W31: X Variable 1 | X31: 0.58998748 | Y31: 0.13506719 | Z31: 4.3681038 | AA31: 2.9944915e-05 | AB31: 0.32211358 | AC31: 0.85786139 | AD31: 0.32211358 | AE31: 0.85786139 | AG31: 45635 | AH31: 642.4 | AI31: =AH31/AH30-1 -> 0.0024968789 | AK31: X Variable 1 | AL31: 1.1732125 | AM31: 0.21056752 | AN31: 5.5716688 | AO31: 2.0289498e-07 | AP31: 0.75560147 | AQ31: 1.5908235 | AR31: 0.75560147 | AS31: 1.5908235 | AU31: 45635 | AV31: 4787.36 | AW31: =AV31/AV30-1 -> -0.0042597091 | AY31: X Variable 1 | AZ31: 0.52697325 | BA31: 0.1482364 | BB31: 3.5549518 | BC31: 0.00057250387 | BD31: 0.23298132 | BE31: 0.82096518 | BF31: 0.23298132 | BG31: 0.82096518
B32: 45642 | C32: 2268.52 | D32: =C32/C31-1 -> -0.023515485 | F32: 23587.5 | G32: =F32/F31-1 -> -0.047673841 | S32: 45642 | T32: 412.38 | U32: =T32/T31-1 -> -0.011387337 | AG32: 45642 | AH32: 609.46 | AI32: =AH32/AH31-1 -> -0.051276463 | AU32: 45642 | AV32: 4637.33 | AW32: =AV32/AV31-1 -> -0.031338775
B33: 45649 | C33: 2275.67 | D33: =C33/C32-1 -> 0.0031518347 | F33: 23813.4 | G33: =F33/F32-1 -> 0.0095771065 | S33: 45649 | T33: 424.77 | U33: =T33/T32-1 -> 0.030045104 | AG33: 45649 | AH33: 621.15 | AI33: =AH33/AH32-1 -> 0.019180914 | AU33: 45649 | AV33: 4707.61 | AW33: =AV33/AV32-1 -> 0.015155273
B34: 45656 | C34: 2338.85 | D34: =C34/C33-1 -> 0.027763252 | F34: 24004.75 | G34: =F34/F33-1 -> 0.0080353918 | S34: 45656 | T34: 427.43 | U34: =T34/T33-1 -> 0.0062622125 | AG34: 45656 | AH34: 648.91 | AI34: =AH34/AH33-1 -> 0.044691298 | AU34: 45656 | AV34: 4771.57 | AW34: =AV34/AV33-1 -> 0.013586512
B35: 45663 | C35: 2373.64 | D35: =C35/C34-1 -> 0.014874832 | F35: 23431.5 | G35: =F35/F34-1 -> -0.02388069 | S35: 45663 | T35: 410.06 | U35: =T35/T34-1 -> -0.040638233 | AG35: 45663 | AH35: 593.54 | AI35: =AH35/AH34-1 -> -0.085327703 | AU35: 45663 | AV35: 4875.31 | AW35: =AV35/AV34-1 -> 0.021741272
B36: 45670 | C36: 2288.06 | D36: =C36/C35-1 -> -0.03605433 | F36: 23203.2 | G36: =F36/F35-1 -> -0.0097432943 | S36: 45670 | T36: 405.73 | U36: =T36/T35-1 -> -0.01055943 | AG36: 45670 | AH36: 553.55 | AI36: =AH36/AH35-1 -> -0.067375409 | AU36: 45670 | AV36: 4791.61 | AW36: =AV36/AV35-1 -> -0.017168139
B37: 45677 | C37: 2301.77 | D37: =C37/C36-1 -> 0.0059919757 | F37: 23092.2 | G37: =F37/F36-1 -> -0.0047838229 | S37: 45677 | T37: 407.02 | U37: =T37/T36-1 -> 0.0031794543 | AG37: 45677 | AH37: 538.97 | AI37: =AH37/AH36-1 -> -0.026339084 | AU37: 45677 | AV37: 5035.56 | AW37: =AV37/AV36-1 -> 0.050911906
B38: 45684 | C38: 2435.85 | D38: =C38/C37-1 -> 0.058250824 | F38: 23482.15 | G38: =F38/F37-1 -> 0.016886654 | S38: 45684 | T38: 426.33 | U38: =T38/T37-1 -> 0.047442386 | AG38: 45684 | AH38: 558.57 | AI38: =AH38/AH37-1 -> 0.03636566 | AU38: 45684 | AV38: 5134.07 | AW38: =AV38/AV37-1 -> 0.019562869
B39: 45691 | C39: 2297.63 | D39: =C39/C38-1 -> -0.056744052 | F39: 23559.95 | G39: =F39/F38-1 -> 0.0033131549 | S39: 45691 | T39: 397.11 | U39: =T39/T38-1 -> -0.068538456 | AG39: 45691 | AH39: 550.91 | AI39: =AH39/AH38-1 -> -0.01371359 | AU39: 45691 | AV39: 4807.5 | AW39: =AV39/AV38-1 -> -0.063608404
B40: 45698 | C40: 2253.41 | D40: =C40/C39-1 -> -0.019245919 | F40: 22929.25 | G40: =F40/F39-1 -> -0.026770006 | S40: 45698 | T40: 378.13 | U40: =T40/T39-1 -> -0.047795321 | AG40: 45698 | AH40: 486.09 | AI40: =AH40/AH39-1 -> -0.11765987 | AU40: 45698 | AV40: 4875.75 | AW40: =AV40/AV39-1 -> 0.014196568
B41: 45705 | C41: 2178.86 | D41: =C41/C40-1 -> -0.033083194 | F41: 22795.9 | G41: =F41/F40-1 -> -0.0058157157 | S41: 45705 | T41: 375.34 | U41: =T41/T40-1 -> -0.0073784148 | AG41: 45705 | AH41: 475.24 | AI41: =AH41/AH40-1 -> -0.022320969 | AU41: 45705 | AV41: 4769.4 | AW41: =AV41/AV40-1 -> -0.021812029
B42: 45712 | C42: 2128.9 | D42: =C42/C41-1 -> -0.022929422 | F42: 22124.7 | G42: =F42/F41-1 -> -0.029443891 | S42: 45712 | T42: 369.82 | U42: =T42/T41-1 -> -0.014706666 | AG42: 45712 | AH42: 433.85 | AI42: =AH42/AH41-1 -> -0.087092837 | AU42: 45712 | AV42: 4536.01 | AW42: =AV42/AV41-1 -> -0.048934877
B43: 45719 | C43: 2142.8 | D43: =C43/C42-1 -> 0.0065291935 | F43: 22552.5 | G43: =F43/F42-1 -> 0.019335855 | S43: 45719 | T43: 378.15 | U43: =T43/T42-1 -> 0.022524471 | AG43: 45719 | AH43: 485.29 | AI43: =AH43/AH42-1 -> 0.11856632 | AU43: 45719 | AV43: 4686.83 | AW43: =AV43/AV42-1 -> 0.033249486
... B112: 46196 | C112: 2166.9 | D112: =C112/C111-1 -> 0.0018493689 | F112: 23831.5 | G112: =F112/F111-1 -> -0.011260056 | S112: 46196 | T112: 290 | U112: =T112/T111-1 -> -0.0042918455 | AG112: 46196 | AH112: 504.3 | AI112: =AH112/AH111-1 -> -0.016863242 | AU112: 46196 | AV112: 5241 | AW112: =AV112/AV111-1 -> 0.0045040728

Sheet Beta - Comps
B2: S.No. | C2: Name | D2: CMP Rs. | E2: Mar Cap Rs.Cr. | F2: Debt Rs.Cr. | G2: Debt / Eq
B3: 1 | C3: Hind. Unilever | D3: 2164.5 | E3: 508569 | F3: 1478 | G3: 0.03
B4: 2 | C4: ITC | D4: 290.2 | E4: 363605.09 | F4: 2399.06 | G4: 0.03
B5: 3 | C5: Varun Beverages | D5: 504.45 | E5: 170619.9 | F5: 2508.18 | G5: 0.13
B6: 4 | C6: Britannia Inds. | D6: 5243.85 | E6: 126307.76 | F6: 1380.28 | G6: 0.27

Sheet Rm
B2: Return on Market
B4: Year | C4: Annual
B5: 2000 | C5: -0.1465 | E5: Average Return | G5: =AVERAGE(C5:C30) -> 0.15149231
B6: 2001 | C6: -0.1618 | E6: Dividend Yield 1 | G6: 0.013
B7: 2002 | C7: 0.0325 | E7: Total Market Return | G7: =SUM(G5:G6) -> 0.16449231
B8: 2003 | C8: 0.719
B9: 2004 | C9: 0.1068 | E9: Geometric return | G9: =GEOMEAN(1+C5:C30)-1 -> 0.1068
B10: 2005 | C10: 0.3634 | E10: Dividend Yield 1 | G10: 0.013
B11: 2006 | C11: 0.3983 | E11: Total Market Return | G11: =SUM(G9:G10) -> 0.1198
B12: 2007 | C12: 0.5477
B13: 2008 | C13: -0.5179
B14: 2009 | C14: 0.7576
B15: 2010 | C15: 0.1795
B16: 2011 | C16: -0.2462
B17: 2012 | C17: 0.277
B18: 2013 | C18: 0.0676
B19: 2014 | C19: 0.3139
B20: 2015 | C20: -0.0406
B21: 2016 | C21: 0.0301
B22: 2017 | C22: 0.2865
B23: 2018 | C23: 0.0315
... B30: 2025 | C30: 0.1051

Sheet Comps Data
B3: S.No. | C3: Name | D3: CMP Rs. | E3: No. Eq. Shares Cr. | F3: Market Cap | G3: Debt Rs.Cr. | H3: Cash End Rs.Cr. | I3: Net Debt | J3: EV | K3: Sales Rs.Cr. | L3: EBITDA | M3: NP 12M Rs.Cr.
B4: 1 | C4: Hind. Unilever | D4: 2157.8 | E4: 234.96 | F4: =E4*D4 -> 506996.69 | G4: 1478 | H4: 3248 | I4: =G4-H4 -> -1770 | J4: =F4+G4-H4 -> 505226.69 | K4: 64468 | L4: 15472.32 | M4: 15059
B5: 2 | C5: ITC | D5: 290.35 | E5: 1252.95 | F5: =E5*D5 -> 363794.03 | G5: 2399.06 | H5: 3008.79 | I5: =G5-H5 -> -609.73 | J5: =F5+G5-H5 -> 363184.3 | K5: 78868.4 | L5: 29969.992 | M5: 21018.15
B6: 3 | C6: Nestle India | D6: 1382.6 | E6: 192.83 | F6: =E6*D6 -> 266606.76 | G6: 444.16 | H6: 1340.87 | I6: =G6-H6 -> -896.71 | J6: =F6+G6-H6 -> 265710.05 | K6: 23154.6 | L6: 5325.558 | M6: 3544.6
B7: 4 | C7: Varun Beverages | D7: 506.7 | E7: 338.23 | F7: =E7*D7 -> 171381.14 | G7: 2508.18 | H7: 1998.49 | I7: =G7-H7 -> 509.69 | J7: =F7+G7-H7 -> 171890.83 | K7: 22692.63 | L7: 5673.1575 | M7: 3209.4
B8: 5 | C8: Britannia Inds. | D8: 5262.5 | E8: 24.09 | F8: =E8*D8 -> 126773.62 | G8: 1380.28 | H8: 352.44 | I8: =G8-H8 -> 1027.84 | J8: =F8+G8-H8 -> 127801.46 | K8: 19151.59 | L8: 3830.318 | M8: 2537.01
B9: 6 | C9: Tata Consumer | D9: 1098.1 | E9: 98.96 | F9: =E9*D9 -> 108667.98 | G9: 2819.51 | H9: 3420.49 | I9: =G9-H9 -> -600.98 | J9: =F9+G9-H9 -> 108067 | K9: 20290.43 | L9: 2840.6602 | M9: 1546.8
B10: 7 | C10: Marico | D10: 819.45 | E10: 129.84 | F10: =E10*D10 -> 106397.39 | G10: 557 | H10: 493 | I10: =G10-H10 -> 64 | J10: =F10+G10-H10 -> 106461.39 | K10: 13611 | L10: 2586.09 | M10: 1813
B11: 8 | C11: Godrej Consumer | D11: 1020.5 | E11: 102.32 | F11: =E11*D11 -> 104417.56 | G11: 4415.81 | H11: 1005.41 | I11: =G11-H11 -> 3410.4 | J11: =F11+G11-H11 -> 107827.96 | K11: 15177.9 | L11: 3490.917 | M11: 1861.47
B12: 9 | C12: United Spirits | D12: 1359.1 | E12: 72.74 | F12: =E12*D12 -> 98860.934 | G12: 413 | H12: 1977 | I12: =G12-H12 -> -1564 | J12: =F12+G12-H12 -> 97296.934 | K12: 12467 | L12: 2742.74 | M12: 1838
B13: 10 | C13: Dabur India | D13: 424.1 | E13: 177.4 | F13: =E13*D13 -> 75235.34 | G13: 1287.32 | H13: 562.07 | I13: =G13-H13 -> 725.25 | J13: =F13+G13-H13 -> 75960.59 | K13: 13192.57 | L13: 3034.2911 | M13: 1868.69
B20: 11 | C20: Colgate-Palmoliv | D20: 1965.3 | E20: 27.2 | F20: =E20*D20 -> 53456.16 | G20: 47.41 | H20: 1468.82 | J20: =F20+G20-H20 -> 52034.75 | K20: 6035.04 | L20: 1931.2128 | M20: 1325.31
B21: 12 | C21: Radico Khaitan | D21: 3757.7 | E21: 13.39 | F21: =E21*D21 -> 50315.603 | G21: 498.44 | H21: 88.33 | J21: =F21+G21-H21 -> 50725.713 | K21: 6050.43 | L21: 1028.5731 | M21: 604.48
B22: 13 | C22: Patanjali Foods | D22: 414.2 | E22: 108.81 | F22: =E22*D22 -> 45069.102 | G22: 2788.83 | H22: 746.36 | J22: =F22+G22-H22 -> 47111.572 | K22: 40169.58 | L22: 2008.479 | M22: 1814.87
B23: 14 | C23: United Breweries | D23: 1336.5 | E23: 26.44 | F23: =E23*D23 -> 35337.06 | G23: 1316.53 | H23: 571.56 | J23: =F23+G23-H23 -> 36082.03 | K23: 9239.94 | L23: 831.5946 | M23: 413.39
B24: 15 | C24: Godfrey Phillips | D24: 2248.4 | E24: 15.6 | F24: =E24*D24 -> 35075.04 | G24: 233.68 | H24: 32.61 | J24: =F24+G24-H24 -> 35276.11 | K24: 6391.11 | L24: 2045.1552 | M24: 1526.02
B25: 16 | C25: P & G Hygiene | D25: 8979 | E25: 3.25 | F25: =E25*D25 -> 29181.75 | G25: 0.87 | H25: 567.94 | J25: =F25+G25-H25 -> 28614.68 | K25: 4290.42 | L25: 1201.3176 | M25: 856.5
B26: 17 | C26: Gillette India | D26: 7793 | E26: 3.26 | F26: =E26*D26 -> 25405.18 | G26: 0.02 | H26: 269.26 | J26: =F26+G26-H26 -> 25135.94 | K26: 3099.53 | L26: 960.8543 | M26: 654.31
B27: 18 | C27: Cupid | D27: 179.48 | E27: 134.47 | F27: =E27*D27 -> 24134.676 | G27: 56.38 | H27: 186.45 | J27: =F27+G27-H27 -> 24004.606 | K27: 391.4 | L27: 148.732 | M27: 108.26
B28: 19 | C28: AWL Agri Busine. | D28: 183.09 | E28: 129.97 | F28: =E28*D28 -> 23796.207 | G28: 1109.27 | H28: 1719.31 | J28: =F28+G28-H28 -> 23186.167 | K28: 74730.67 | L28: 2241.9201 | M28: 1044.89
B29: 20 | C29: Hatsun Agro | D29: 913.35 | E29: 22.27 | F29: =E29*D29 -> 20340.304 | G29: 1838.25 | H29: 51.19 | J29: =F29+G29-H29 -> 22127.364 | K29: 9959.22 | L29: 1195.1064 | M29: 356.2
B30: 21 | C30: Emami | D30: 403.9 | E30: 43.65 | F30: =E30*D30 -> 17630.235 | G30: 161.92 | H30: 409.84 | J30: =F30+G30-H30 -> 17382.315 | K30: 3779.51 | L30: 1058.2628 | M30: 775.26
B31: 22 | C31: Allied Blenders | D31: 629.05 | E31: 27.97 | F31: =E31*D31 -> 17594.528 | G31: 1150.53 | H31: 165.18 | J31: =F31+G31-H31 -> 18579.878 | K31: 3922.78 | L31: 549.1892 | M31: 220.12
... B34: 25 | C34: CCL Products | D34: 1167.1 | E34: 13.35 | F34: =E34*D34 -> 15580.785 | G34: 1324.36 | H34: 217.55 | J34: =F34+G34-H34 -> 16687.595 | K34: 4457.37 | L34: 757.7529 | M34: 388.1

Sheet Financials>

Sheet HistoricalFS
B2: ="Historical Financial Statement - "&'Data Sheet'!B1 -> Historical Financial Statement - HINDUSTAN UNILEVER LTD
B3: Years | C3: ='Data Sheet'!C16 -> 43190 | D3: ='Data Sheet'!D16 -> 43555 | E3: ='Data Sheet'!E16 -> 43921 | F3: ='Data Sheet'!F16 -> 44286 | G3: ='Data Sheet'!G16 -> 44651 | H3: ='Data Sheet'!H16 -> 45016 | I3: ='Data Sheet'!I16 -> 45382 | J3: ='Data Sheet'!J16 -> 45747 | K3: ='Data Sheet'!K16 -> 46112 | L3: LTM
A5: # | B5: Income Statement
B6: Sales | C6: =IFERROR('Data Sheet'!C17,0) -> 35545 | D6: =IFERROR('Data Sheet'!D17,0) -> 39310 | E6: =IFERROR('Data Sheet'!E17,0) -> 39783 | F6: =IFERROR('Data Sheet'!F17,0) -> 47028 | G6: =IFERROR('Data Sheet'!G17,0) -> 52446 | H6: =IFERROR('Data Sheet'!H17,0) -> 60580 | I6: =IFERROR('Data Sheet'!I17,0) -> 61896 | J6: =IFERROR('Data Sheet'!J17,0) -> 61328 | K6: =IFERROR('Data Sheet'!K17,0) -> 64468 | L6: =IFERROR(SUM('Data Sheet'!H42:K42),0) -> 65225
B7: Sales Growth | C7: - | D7: =D6/C6-1 -> 0.10592207 | E7: =E6/D6-1 -> 0.012032562 | F7: =F6/E6-1 -> 0.18211296 | G7: =G6/F6-1 -> 0.11520796 | H7: =H6/G6-1 -> 0.15509286 | I7: =I6/H6-1 -> 0.021723341 | J7: =J6/I6-1 -> -0.0091766835 | K7: =K6/J6-1 -> 0.051200104 | L7: =L6/K6-1 -> 0.01174226
B9: COGS | C9: =IFERROR(SUM('Data Sheet'!C18,'Data Sheet'!C20,'Data Sheet'!C21,'Data Sheet'!C22)-1*'Data Sheet'!C19,0) -> 19314 | D9: =IFERROR(SUM('Data Sheet'!D18,'Data Sheet'!D20,'Data Sheet'!D21,'Data Sheet'!D22)-1*'Data Sheet'!D19,0) -> 21081 | E9: =IFERROR(SUM('Data Sheet'!E18,'Data Sheet'!E20,'Data Sheet'!E21,'Data Sheet'!E22)-1*'Data Sheet'!E19,0) -> 20614 | F9: =IFERROR(SUM('Data Sheet'!F18,'Data Sheet'!F20,'Data Sheet'!F21,'Data Sheet'!F22)-1*'Data Sheet'!F19,0) -> 25301 | G9: =IFERROR(SUM('Data Sheet'!G18,'Data Sheet'!G20,'Data Sheet'!G21,'Data Sheet'!G22)-1*'Data Sheet'!G19,0) -> 29066 | H9: =IFERROR(SUM('Data Sheet'!H18,'Data Sheet'!H20,'Data Sheet'!H21,'Data Sheet'!H22)-1*'Data Sheet'!H19,0) -> 35381 | I9: =IFERROR(SUM('Data Sheet'!I18,'Data Sheet'!I20,'Data Sheet'!I21,'Data Sheet'!I22)-1*'Data Sheet'!I19,0) -> 33651 | J9: =IFERROR(SUM('Data Sheet'!J18,'Data Sheet'!J20,'Data Sheet'!J21,'Data Sheet'!J22)-1*'Data Sheet'!J19,0) -> 33519 | K9: =IFERROR(SUM('Data Sheet'!K18,'Data Sheet'!K20,'Data Sheet'!K21,'Data Sheet'!K22)-1*'Data Sheet'!K19,0) -> 35634 | L9: =IFERROR(SUM('Data Sheet'!H43:K43),0) -> 50108
B10: COGS % Sales | C10: =C9/C6 -> 0.54336756 | D10: =D9/D6 -> 0.53627576 | E10: =E9/E6 -> 0.51816102 | F10: =F9/F6 -> 0.53799864 | G10: =G9/G6 -> 0.55420814 | H10: =H9/H6 -> 0.58403764 | I10: =I9/I6 -> 0.54367003 | J10: =J9/J6 -> 0.54655296 | ... L10: =L9/L6 -> 0.76823304
B12: Gross Profit | C12: =C6-C9 -> 16231 | D12: =D6-D9 -> 18229 | E12: =E6-E9 -> 19169 | F12: =F6-F9 -> 21727 | G12: =G6-G9 -> 23380 | H12: =H6-H9 -> 25199 | I12: =I6-I9 -> 28245 | J12: =J6-J9 -> 27809 | ... L12: =L6-L9 -> 15117
B13: Gross Margin | C13: =C12/C6 -> 0.45663244 | D13: =D12/D6 -> 0.46372424 | E13: =E12/E6 -> 0.48183898 | F13: =F12/F6 -> 0.46200136 | G13: =G12/G6 -> 0.44579186 | H13: =H12/H6 -> 0.41596236 | I13: =I12/I6 -> 0.45632997 | J13: =J12/J6 -> 0.45344704 | ... L13: =L12/L6 -> 0.23176696
B15: Selling & General Expenses | C15: =IFERROR(SUM('Data Sheet'!C23:C24),0) -> 8732 | D15: =IFERROR(SUM('Data Sheet'!D23:D24),0) -> 9349 | E15: =IFERROR(SUM('Data Sheet'!E23:E24),0) -> 9308 | F15: =IFERROR(SUM('Data Sheet'!F23:F24),0) -> 10101 | G15: =IFERROR(SUM('Data Sheet'!G23:G24),0) -> 10523 | H15: =IFERROR(SUM('Data Sheet'!H23:H24),0) -> 11052 | I15: =IFERROR(SUM('Data Sheet'!I23:I24),0) -> 13586 | J15: =IFERROR(SUM('Data Sheet'!J23:J24),0) -> 13111 | ... L15: =IFERROR(SUM('Data Sheet'!L23:L24),0) -> 0
B16: S&G Exp % Sales | C16: =C15/C6 -> 0.24566043 | D16: =D15/D6 -> 0.23782752 | E16: =E15/E6 -> 0.23396928 | F16: =F15/F6 -> 0.21478694 | G16: =G15/G6 -> 0.20064447 | H16: =H15/H6 -> 0.18243645 | I16: =I15/I6 -> 0.21949722 | J16: =J15/J6 -> 0.21378489 | ... L16: =L15/L6 -> 0
B18: EBITDA | C18: =C12-C15 -> 7499 | D18: =D12-D15 -> 8880 | E18: =E12-E15 -> 9861 | F18: =F12-F15 -> 11626 | G18: =G12-G15 -> 12857 | H18: =H12-H15 -> 14147 | I18: =I12-I15 -> 14659 | J18: =J12-J15 -> 14698 | ... L18: =L12-L15 -> 15117
B19: EBITDA % Sales | C19: =C18/C6 -> 0.21097201 | D19: =D18/D6 -> 0.22589672 | E19: =E18/E6 -> 0.24786969 | F19: =F18/F6 -> 0.24721443 | G19: =G18/G6 -> 0.24514739 | H19: =H18/H6 -> 0.23352592 | I19: =I18/I6 -> 0.23683275 | J19: =J18/J6 -> 0.23966214 | ... L19: =L18/L6 -> 0.23176696
B21: Depreciation | C21: =IFERROR('Data Sheet'!C26,0) -> 520 | D21: =IFERROR('Data Sheet'!D26,0) -> 565 | E21: =IFERROR('Data Sheet'!E26,0) -> 1002 | F21: =IFERROR('Data Sheet'!F26,0) -> 1074 | G21: =IFERROR('Data Sheet'!G26,0) -> 1091 | H21: =IFERROR('Data Sheet'!H26,0) -> 1137 | I21: =IFERROR('Data Sheet'!I26,0) -> 1216 | J21: =IFERROR('Data Sheet'!J26,0) -> 1253 | K21: =IFERROR('Data Sheet'!K26,0) -> 1333 | L21: =IFERROR(SUM('Data Sheet'!H45:K45),0) -> 1368
B22: Depreciation % Sales | C22: =C21/C6 -> 0.014629343 | D22: =D21/D6 -> 0.014372933 | E22: =E21/E6 -> 0.025186638 | F22: =F21/F6 -> 0.022837459 | G22: =G21/G6 -> 0.020802349 | H22: =H21/H6 -> 0.01876857 | I22: =I21/I6 -> 0.019645858 | J22: =J21/J6 -> 0.020431124 | ... L22: =L21/L6 -> 0.020973553
B24: EBIT | C24: =IFERROR((C18-C21),0) -> 6979 | D24: =IFERROR((D18-D21),0) -> 8315 | E24: =IFERROR((E18-E21),0) -> 8859 | F24: =IFERROR((F18-F21),0) -> 10552 | G24: =IFERROR((G18-G21),0) -> 11766 | H24: =IFERROR((H18-H21),0) -> 13010 | I24: =IFERROR((I18-I21),0) -> 13443 | J24: =IFERROR((J18-J21),0) -> 13445 | ... L24: =IFERROR((L18-L21),0) -> 13749
B25: EBIT % Sales | C25: =IFERROR(C24/C6,0) -> 0.19634266 | D25: =IFERROR(D24/D6,0) -> 0.21152379 | E25: =IFERROR(E24/E6,0) -> 0.22268306 | F25: =IFERROR(F24/F6,0) -> 0.22437697 | G25: =IFERROR(G24/G6,0) -> 0.22434504 | H25: =IFERROR(H24/H6,0) -> 0.21475735 | I25: =IFERROR(I24/I6,0) -> 0.21718689 | J25: =IFERROR(J24/J6,0) -> 0.21923102 | ... L25: =IFERROR(L24/L6,0) -> 0.21079341
B27: Interest | C27: =IFERROR('Data Sheet'!C27,0) -> 26 | D27: =IFERROR('Data Sheet'!D27,0) -> 33 | E27: =IFERROR('Data Sheet'!E27,0) -> 118 | F27: =IFERROR('Data Sheet'!F27,0) -> 117 | G27: =IFERROR('Data Sheet'!G27,0) -> 106 | H27: =IFERROR('Data Sheet'!H27,0) -> 114 | I27: =IFERROR('Data Sheet'!I27,0) -> 334 | J27: =IFERROR('Data Sheet'!J27,0) -> 381 | K27: =IFERROR('Data Sheet'!K27,0) -> 410 | L27: =IFERROR(SUM('Data Sheet'!H46:K46),0) -> 415
B28: Interest % Sales | C28: =C27/C6 -> 0.00073146715 | D28: =D27/D6 -> 0.00083948105 | E28: =E27/E6 -> 0.002966091 | F28: =F27/F6 -> 0.0024878796 | G28: =G27/G6 -> 0.0020211265 | H28: =H27/H6 -> 0.0018818092 | I28: =I27/I6 -> 0.0053961484 | J28: =J27/J6 -> 0.0062124967 | ... L28: =L27/L6 -> 0.006362591
B30: Earnings Before Tax | C30: =IFERROR(C24-C27,0) -> 6953 | D30: =IFERROR(D24-D27,0) -> 8282 | E30: =IFERROR(E24-E27,0) -> 8741 | F30: =IFERROR(F24-F27,0) -> 10435 | G30: =IFERROR(G24-G27,0) -> 11660 | H30: =IFERROR(H24-H27,0) -> 12896 | I30: =IFERROR(I24-I27,0) -> 13109 | J30: =IFERROR(J24-J27,0) -> 13064 | ... L30: =IFERROR(L24-L27,0) -> 13334
B31: EBT % Sales | C31: =C30/C6 -> 0.1956112 | D31: =D30/D6 -> 0.2106843 | E31: =E30/E6 -> 0.21971696 | F31: =F30/F6 -> 0.22188909 | G31: =G30/G6 -> 0.22232391 | H31: =H30/H6 -> 0.21287554 | I31: =I30/I6 -> 0.21179075 | J31: =J30/J6 -> 0.21301852 | ... L31: =L30/L6 -> 0.20443082
B33: Tax | C33: =IFERROR('Data Sheet'!C29,0) -> 2079 | D33: =IFERROR('Data Sheet'!D29,0) -> 2544 | E33: =IFERROR('Data Sheet'!E29,0) -> 2409 | F33: =IFERROR('Data Sheet'!F29,0) -> 2606 | G33: =IFERROR('Data Sheet'!G29,0) -> 2987 | H33: =IFERROR('Data Sheet'!H29,0) -> 3201 | I33: =IFERROR('Data Sheet'!I29,0) -> 3644 | J33: =IFERROR('Data Sheet'!J29,0) -> 3748 | K33: =IFERROR('Data Sheet'!K29,0) -> 3160 | L33: =IFERROR(SUM('Data Sheet'!H48:K48),0) -> 3169
B34: Effective Tax Rate | C34: =C33/C30 -> 0.29900762 | D34: =D33/D30 -> 0.30717218 | E34: =E33/E30 -> 0.27559776 | F34: =F33/F30 -> 0.24973646 | G34: =G33/G30 -> 0.25617496 | H34: =H33/H30 -> 0.2482165 | I34: =I33/I30 -> 0.27797696 | J34: =J33/J30 -> 0.28689528 | ... L34: =L33/L30 -> 0.23766312
B36: Net Profit | C36: =IFERROR(C30-C33,0) -> 4874 | D36: =IFERROR(D30-D33,0) -> 5738 | E36: =IFERROR(E30-E33,0) -> 6332 | F36: =IFERROR(F30-F33,0) -> 7829 | G36: =IFERROR(G30-G33,0) -> 8673 | H36: =IFERROR(H30-H33,0) -> 9695 | I36: =IFERROR(I30-I33,0) -> 9465 | J36: =IFERROR(J30-J33,0) -> 9316 | ... L36: =IFERROR(L30-L33,0) -> 10165
B37: Net Margins | C37: =C36/C6 -> 0.13712196 | D37: =D36/D6 -> 0.14596795 | E37: =E36/E6 -> 0.15916346 | F37: =F36/F6 -> 0.16647529 | G37: =G36/G6 -> 0.16537009 | H37: =H36/H6 -> 0.16003632 | I37: =I36/I6 -> 0.1529178 | J37: =J36/J6 -> 0.15190451 | ... L37: =L36/L6 -> 0.15584515
B39: No of Equity Shares | C39: =IFERROR('Data Sheet'!B93,0) -> 216.43 | D39: =IFERROR('Data Sheet'!C93,0) -> 216.45 | E39: =IFERROR('Data Sheet'!D93,0) -> 216.47 | F39: =IFERROR('Data Sheet'!E93,0) -> 216.48 | G39: =IFERROR('Data Sheet'!F93,0) -> 234.96 | H39: =IFERROR('Data Sheet'!G93,0) -> 234.96 | I39: =IFERROR('Data Sheet'!H93,0) -> 234.96 | J39: =IFERROR('Data Sheet'!I93,0) -> 234.96 | ... L39: =IFERROR('Data Sheet'!K93,0) -> 234.96
B41: Earning per Share | C41: =IFERROR(C36/C39,0) -> 22.519983 | D41: =IFERROR(D36/D39,0) -> 26.509587 | E41: =IFERROR(E36/E39,0) -> 29.251166 | F41: =IFERROR(F36/F39,0) -> 36.165004 | G41: =IFERROR(G36/G39,0) -> 36.912666 | H41: =IFERROR(H36/H39,0) -> 41.262343 | I41: =IFERROR(I36/I39,0) -> 40.283453 | J41: =IFERROR(J36/J39,0) -> 39.649302 | ... L41: =IFERROR(L36/L39,0) -> 43.262683
B42: EPS Growth % | D42: =IFERROR(D41/C41-1,0) -> 0.17715835 | E42: =IFERROR(E41/D41-1,0) -> 0.10341843 | F42: =IFERROR(F41/E41-1,0) -> 0.23636108 | G42: =IFERROR(G41/F41-1,0) -> 0.020673641 | H42: =IFERROR(H41/G41-1,0) -> 0.11783697 | I42: =IFERROR(I41/H41-1,0) -> -0.023723569 | J42: =IFERROR(J41/I41-1,0) -> -0.015742208 | K42: =IFERROR(K41/J41-1,0) -> 0.08802061 | L42: =IFERROR(L41/K41-1,0) -> 0.0028610892
B44: Dividend Per Share | C44: =IFERROR('Data Sheet'!C31/HistoricalFS!C39,0) -> 19.960264 | D44: =IFERROR('Data Sheet'!D31/HistoricalFS!D39,0) -> 21.954262 | E44: =IFERROR('Data Sheet'!E31/HistoricalFS!E39,0) -> 24.94572 | F44: =IFERROR('Data Sheet'!F31/HistoricalFS!F39,0) -> 43.9648 | G44: =IFERROR('Data Sheet'!G31/HistoricalFS!G39,0) -> 34.005788 | H44: =IFERROR('Data Sheet'!H31/HistoricalFS!H39,0) -> 39.006639 | I44: =IFERROR('Data Sheet'!I31/HistoricalFS!I39,0) -> 42.00715 | J44: =IFERROR('Data Sheet'!J31/HistoricalFS!J39,0) -> 53.009023 | ... L44: =IFERROR('Data Sheet'!L31/HistoricalFS!L39,0) -> 0
B45: Dividend Payout Ratio | C45: =IFERROR(C44/C41,0) -> 0.88633566 | D45: =IFERROR(D44/D41,0) -> 0.82816312 | E45: =IFERROR(E44/E41,0) -> 0.85281112 | F45: =IFERROR(F44/F41,0) -> 1.2156725 | G45: =IFERROR(G44/G41,0) -> 0.92124986 | H45: =IFERROR(H44/H41,0) -> 0.94533265 | I45: =IFERROR(I44/I41,0) -> 1.0427892 | J45: =IFERROR(J44/J41,0) -> 1.3369472 | K45: =IFERROR(K44/K41,0) -> 0.95057222 | L45: =IFERROR(L41/L44,0) -> 0
B47: Retained Earnings | C47: =IFERROR(IF(C41>C44,1-C45,0),0) -> 0.11366434 | D47: =IFERROR(IF(D41>D44,1-D45,0),0) -> 0.17183688 | E47: =IFERROR(IF(E41>E44,1-E45,0),0) -> 0.14718888 | F47: =IFERROR(IF(F41>F44,1-F45,0),0) -> 0 | G47: =IFERROR(IF(G41>G44,1-G45,0),0) -> 0.078750144 | H47: =IFERROR(IF(H41>H44,1-H45,0),0) -> 0.054667354 | I47: =IFERROR(IF(I41>I44,1-I45,0),0) -> 0 | J47: =IFERROR(IF(J41>J44,1-J45,0),0) -> 0 | ... L47: =IFERROR(IF(L41>L44,1-L45,0),0) -> 1
A54: # | B54: Balance Sheet
B55: Equity Share Capital | C55: =IFERROR('Data Sheet'!C57,0) -> 216 | D55: =IFERROR('Data Sheet'!D57,0) -> 216 | E55: =IFERROR('Data Sheet'!E57,0) -> 216 | F55: =IFERROR('Data Sheet'!F57,0) -> 235 | G55: =IFERROR('Data Sheet'!G57,0) -> 235 | H55: =IFERROR('Data Sheet'!H57,0) -> 235 | I55: =IFERROR('Data Sheet'!I57,0) -> 235 | J55: =IFERROR('Data Sheet'!J57,0) -> 235 | K55: =IFERROR('Data Sheet'!K57,0) -> 235
B56: Reserves | C56: =IFERROR('Data Sheet'!C58,0) -> 7065 | D56: =IFERROR('Data Sheet'!D58,0) -> 7651 | E56: =IFERROR('Data Sheet'!E58,0) -> 8013 | F56: =IFERROR('Data Sheet'!F58,0) -> 47439 | G56: =IFERROR('Data Sheet'!G58,0) -> 48826 | H56: =IFERROR('Data Sheet'!H58,0) -> 50069 | I56: =IFERROR('Data Sheet'!I58,0) -> 50983 | J56: =IFERROR('Data Sheet'!J58,0) -> 49167 | K56: =IFERROR('Data Sheet'!K58,0) -> 48504
B57: Borrowings | C57: =IFERROR('Data Sheet'!C59,0) -> 0 | D57: =IFERROR('Data Sheet'!D59,0) -> 99 | E57: =IFERROR('Data Sheet'!E59,0) -> 0 | F57: =IFERROR('Data Sheet'!F59,0) -> 0 | G57: =IFERROR('Data Sheet'!G59,0) -> 1043 | H57: =IFERROR('Data Sheet'!H59,0) -> 1219 | I57: =IFERROR('Data Sheet'!I59,0) -> 1484 | J57: =IFERROR('Data Sheet'!J59,0) -> 1648 | K57: =IFERROR('Data Sheet'!K59,0) -> 1478
B58: Other Liabilities | C58: =IFERROR('Data Sheet'!C60,0) -> 10581 | D58: =IFERROR('Data Sheet'!D60,0) -> 10663 | E58: =IFERROR('Data Sheet'!E60,0) -> 11924 | F58: =IFERROR('Data Sheet'!F60,0) -> 21066 | G58: =IFERROR('Data Sheet'!G60,0) -> 20402 | H58: =IFERROR('Data Sheet'!H60,0) -> 21554 | I58: =IFERROR('Data Sheet'!I60,0) -> 25787 | J58: =IFERROR('Data Sheet'!J60,0) -> 28813 | K58: =IFERROR('Data Sheet'!K60,0) -> 29521
B59: Total Liabilities | C59: =IFERROR('Data Sheet'!C61,0) -> 17862 | D59: =IFERROR('Data Sheet'!D61,0) -> 18629 | E59: =IFERROR('Data Sheet'!E61,0) -> 20153 | F59: =IFERROR('Data Sheet'!F61,0) -> 68740 | G59: =IFERROR('Data Sheet'!G61,0) -> 70506 | H59: =IFERROR('Data Sheet'!H61,0) -> 73077 | I59: =IFERROR('Data Sheet'!I61,0) -> 78489 | J59: =IFERROR('Data Sheet'!J61,0) -> 79863 | K59: =IFERROR('Data Sheet'!K61,0) -> 79738
B61: Fixed Assets Net Block | C61: =IFERROR('Data Sheet'!C62,0) -> 4528 | D61: =IFERROR('Data Sheet'!D62,0) -> 4715 | E61: =IFERROR('Data Sheet'!E62,0) -> 5479 | F61: =IFERROR('Data Sheet'!F62,0) -> 51443 | G61: =IFERROR('Data Sheet'!G62,0) -> 51473 | H61: =IFERROR('Data Sheet'!H62,0) -> 52678 | I61: =IFERROR('Data Sheet'!I62,0) -> 53744 | J61: =IFERROR('Data Sheet'!J62,0) -> 54335 | K61: =IFERROR('Data Sheet'!K62,0) -> 57428
B62: Capital Work in Progress | C62: =IFERROR('Data Sheet'!C63,0) -> 461 | D62: =IFERROR('Data Sheet'!D63,0) -> 406 | E62: =IFERROR('Data Sheet'!E63,0) -> 597 | F62: =IFERROR('Data Sheet'!F63,0) -> 745 | G62: =IFERROR('Data Sheet'!G63,0) -> 1313 | H62: =IFERROR('Data Sheet'!H63,0) -> 1132 | I62: =IFERROR('Data Sheet'!I63,0) -> 1025 | J62: =IFERROR('Data Sheet'!J63,0) -> 1009 | K62: =IFERROR('Data Sheet'!K63,0) -> 880
B63: Investments | C63: =IFERROR('Data Sheet'!C64,0) -> 2873 | D63: =IFERROR('Data Sheet'!D64,0) -> 2716 | E63: =IFERROR('Data Sheet'!E64,0) -> 1255 | F63: =IFERROR('Data Sheet'!F64,0) -> 2709 | G63: =IFERROR('Data Sheet'!G64,0) -> 3521 | H63: =IFERROR('Data Sheet'!H64,0) -> 2882 | I63: =IFERROR('Data Sheet'!I64,0) -> 4625 | J63: =IFERROR('Data Sheet'!J64,0) -> 3810 | K63: =IFERROR('Data Sheet'!K64,0) -> 4359
B64: Other Assets | C64: =IFERROR('Data Sheet'!C65-SUM('Data Sheet'!C67:C69),0) -> 2692 | D64: =IFERROR('Data Sheet'!D65-SUM('Data Sheet'!D67:D69),0) -> 2645 | E64: =IFERROR('Data Sheet'!E65-SUM('Data Sheet'!E67:E69),0) -> 3793 | F64: =IFERROR('Data Sheet'!F65-SUM('Data Sheet'!F67:F69),0) -> 4035 | G64: =IFERROR('Data Sheet'!G65-SUM('Data Sheet'!G67:G69),0) -> 4021 | H64: =IFERROR('Data Sheet'!H65-SUM('Data Sheet'!H67:H69),0) -> 4377 | I64: =IFERROR('Data Sheet'!I65-SUM('Data Sheet'!I67:I69),0) -> 4517 | J64: =IFERROR('Data Sheet'!J65-SUM('Data Sheet'!J67:J69),0) -> 4921 | K64: =IFERROR('Data Sheet'!K65-SUM('Data Sheet'!K67:K69),0) -> 5655
B65: Total Non Current Assets | C65: =IFERROR(SUM(C61:C64),0) -> 10554 | D65: =IFERROR(SUM(D61:D64),0) -> 10482 | E65: =IFERROR(SUM(E61:E64),0) -> 11124 | F65: =IFERROR(SUM(F61:F64),0) -> 58932 | G65: =IFERROR(SUM(G61:G64),0) -> 60328 | H65: =IFERROR(SUM(H61:H64),0) -> 61069 | I65: =IFERROR(SUM(I61:I64),0) -> 63911 | J65: =IFERROR(SUM(J61:J64),0) -> 64075 | K65: =IFERROR(SUM(K61:K64),0) -> 68322
B67: Receivables | C67: =IFERROR('Data Sheet'!C67,0) -> 1310 | D67: =IFERROR('Data Sheet'!D67,0) -> 1816 | E67: =IFERROR('Data Sheet'!E67,0) -> 1149 | F67: =IFERROR('Data Sheet'!F67,0) -> 1758 | G67: =IFERROR('Data Sheet'!G67,0) -> 2236 | H67: =IFERROR('Data Sheet'!H67,0) -> 3079 | I67: =IFERROR('Data Sheet'!I67,0) -> 2997 | J67: =IFERROR('Data Sheet'!J67,0) -> 3819 | K67: =IFERROR('Data Sheet'!K67,0) -> 3379
B68: Inventory | C68: =IFERROR('Data Sheet'!C68,0) -> 2513 | D68: =IFERROR('Data Sheet'!D68,0) -> 2574 | E68: =IFERROR('Data Sheet'!E68,0) -> 2767 | F68: =IFERROR('Data Sheet'!F68,0) -> 3579 | G68: =IFERROR('Data Sheet'!G68,0) -> 4096 | H68: =IFERROR('Data Sheet'!H68,0) -> 4251 | I68: =IFERROR('Data Sheet'!I68,0) -> 4022 | J68: =IFERROR('Data Sheet'!J68,0) -> 4415 | K68: =IFERROR('Data Sheet'!K68,0) -> 4789
B69: Cash & Bank | C69: =IFERROR('Data Sheet'!C69,0) -> 3485 | D69: =IFERROR('Data Sheet'!D69,0) -> 3757 | E69: =IFERROR('Data Sheet'!E69,0) -> 5113 | F69: =IFERROR('Data Sheet'!F69,0) -> 4471 | G69: =IFERROR('Data Sheet'!G69,0) -> 3846 | H69: =IFERROR('Data Sheet'!H69,0) -> 4678 | I69: =IFERROR('Data Sheet'!I69,0) -> 7559 | J69: =IFERROR('Data Sheet'!J69,0) -> 7554 | K69: =IFERROR('Data Sheet'!K69,0) -> 3248
B70: Total Current Assets | C70: =IFERROR(SUM(C67:C69),0) -> 7308 | D70: =IFERROR(SUM(D67:D69),0) -> 8147 | E70: =IFERROR(SUM(E67:E69),0) -> 9029 | F70: =IFERROR(SUM(F67:F69),0) -> 9808 | G70: =IFERROR(SUM(G67:G69),0) -> 10178 | H70: =IFERROR(SUM(H67:H69),0) -> 12008 | I70: =IFERROR(SUM(I67:I69),0) -> 14578 | J70: =IFERROR(SUM(J67:J69),0) -> 15788 | K70: =IFERROR(SUM(K67:K69),0) -> 11416
B72: Total Assets | C72: =IFERROR(SUM(C65,C70),0) -> 17862 | D72: =IFERROR(SUM(D65,D70),0) -> 18629 | E72: =IFERROR(SUM(E65,E70),0) -> 20153 | F72: =IFERROR(SUM(F65,F70),0) -> 68740 | G72: =IFERROR(SUM(G65,G70),0) -> 70506 | H72: =IFERROR(SUM(H65,H70),0) -> 73077 | I72: =IFERROR(SUM(I65,I70),0) -> 78489 | J72: =IFERROR(SUM(J65,J70),0) -> 79863 | K72: =IFERROR(SUM(K65,K70),0) -> 79738
B74: Check | C74: =C72=C59 -> TRUE | D74: =D72=D59 -> TRUE | E74: =E72=E59 -> TRUE | F74: =F72=F59 -> TRUE | G74: =G72=G59 -> TRUE | H74: =H72=H59 -> TRUE | I74: =I72=I59 -> TRUE | J74: =J72=J59 -> TRUE | K74: =K72=K59 -> TRUE
A76: # | B76: Cash Flow Statement
B77: Operating Activities
B78: Profit from operations | C78: ='Raw FS'!F46 -> 7485 | D78: ='Raw FS'!G46 -> 8909 | E78: ='Raw FS'!H46 -> 9723 | F78: ='Raw FS'!I46 -> 11672 | G78: ='Raw FS'!J46 -> 12829 | H78: ='Raw FS'!K46 -> 14089 | I78: ='Raw FS'!L46 -> 14537 | J78: ='Raw FS'!M46 -> 14942 | K78: ='Raw FS'!N46 -> 15153
B79: Receivables | C79: ='Raw FS'!F47 -> 0 | D79: ='Raw FS'!G47 -> 0 | E79: ='Raw FS'!H47 -> 0 | F79: ='Raw FS'!I47 -> 0 | G79: ='Raw FS'!J47 -> 0 | H79: ='Raw FS'!K47 -> 0 | I79: ='Raw FS'!L47 -> 0 | J79: ='Raw FS'!M47 -> 0 | K79: ='Raw FS'!N47 -> 0
B80: Inventory | C80: ='Raw FS'!F48 -> -146 | D80: ='Raw FS'!G48 -> -195 | E80: ='Raw FS'!H48 -> -331 | F80: ='Raw FS'!I48 -> -543 | G80: ='Raw FS'!J48 -> -758 | H80: ='Raw FS'!K48 -> -339 | I80: ='Raw FS'!L48 -> 74 | J80: ='Raw FS'!M48 -> -584 | K80: ='Raw FS'!N48 -> -692
B81: Payables | C81: ='Raw FS'!F49 -> 0 | D81: ='Raw FS'!G49 -> 0 | E81: ='Raw FS'!H49 -> 0 | F81: ='Raw FS'!I49 -> 0 | G81: ='Raw FS'!J49 -> 0 | H81: ='Raw FS'!K49 -> 0 | I81: ='Raw FS'!L49 -> 0 | J81: ='Raw FS'!M49 -> 0 | K81: ='Raw FS'!N49 -> 0
B82: Loans Advances | C82: ='Raw FS'!F50 -> 0 | D82: ='Raw FS'!G50 -> 0 | E82: ='Raw FS'!H50 -> 0 | F82: ='Raw FS'!I50 -> 0 | G82: ='Raw FS'!J50 -> 0 | H82: ='Raw FS'!K50 -> 0 | I82: ='Raw FS'!L50 -> 0 | J82: ='Raw FS'!M50 -> 0 | K82: ='Raw FS'!N50 -> 0
B83: Operating Deposits | C83: ='Raw FS'!F51 -> 0 | D83: ='Raw FS'!G51 -> 0 | E83: ='Raw FS'!H51 -> 0 | F83: ='Raw FS'!I51 -> 0 | G83: ='Raw FS'!J51 -> 0 | H83: ='Raw FS'!K51 -> 0 | I83: ='Raw FS'!L51 -> 0 | J83: ='Raw FS'!M51 -> 0 | K83: ='Raw FS'!N51 -> 0
B84: Other WC items | C84: ='Raw FS'!F52 -> 982 | D84: ='Raw FS'!G52 -> -147 | E84: ='Raw FS'!H52 -> 742 | F84: ='Raw FS'!I52 -> 442 | G84: ='Raw FS'!J52 -> -242 | H84: ='Raw FS'!K52 -> -621 | I84: ='Raw FS'!L52 -> 1239 | J84: ='Raw FS'!M52 -> -204 | K84: ='Raw FS'!N52 -> 1378
B85: Working capital changes | C85: ='Raw FS'!F53 -> 836 | D85: ='Raw FS'!G53 -> -342 | E85: ='Raw FS'!H53 -> 411 | F85: ='Raw FS'!I53 -> -101 | G85: ='Raw FS'!J53 -> -1000 | H85: ='Raw FS'!K53 -> -960 | I85: ='Raw FS'!L53 -> 1313 | J85: ='Raw FS'!M53 -> -788 | K85: ='Raw FS'!N53 -> 686
B86: Direct taxes | C86: ='Raw FS'!F54 -> -2264 | D86: ='Raw FS'!G54 -> -2767 | E86: ='Raw FS'!H54 -> -2505 | F86: ='Raw FS'!I54 -> -2407 | G86: ='Raw FS'!J54 -> -2784 | H86: ='Raw FS'!K54 -> -3138 | I86: ='Raw FS'!L54 -> -381 | J86: ='Raw FS'!M54 -> -2268 | K86: ='Raw FS'!N54 -> -4840
B87: Other operating items | C87: ='Raw FS'!F55 -> 0 | D87: ='Raw FS'!G55 -> 0 | E87: ='Raw FS'!H55 -> 0 | F87: ='Raw FS'!I55 -> 0 | G87: ='Raw FS'!J55 -> 0 | H87: ='Raw FS'!K55 -> 0 | I87: ='Raw FS'!L55 -> 0 | J87: ='Raw FS'!M55 -> 0 | K87: ='Raw FS'!N55 -> 0
B88: Exceptional CF items | C88: ='Raw FS'!F56 -> 2 | D88: ='Raw FS'!G56 -> 0 | E88: ='Raw FS'!H56 -> -6 | F88: ='Raw FS'!I56 -> -1 | G88: ='Raw FS'!J56 -> 3 | H88: ='Raw FS'!K56 -> 0 | I88: ='Raw FS'!L56 -> 0 | J88: ='Raw FS'!M56 -> 0 | K88: ='Raw FS'!N56 -> 0
B89: Cash Flow From Operating Activities | C89: =IFERROR(SUM(C78:C88),0) -> 6895 | D89: =IFERROR(SUM(D78:D88),0) -> 5458 | E89: =IFERROR(SUM(E78:E88),0) -> 8034 | F89: =IFERROR(SUM(F78:F88),0) -> 9062 | G89: =IFERROR(SUM(G78:G88),0) -> 8048 | H89: =IFERROR(SUM(H78:H88),0) -> 9031 | I89: =IFERROR(SUM(I78:I88),0) -> 16782 | J89: =IFERROR(SUM(J78:J88),0) -> 11098 | K89: =IFERROR(SUM(K78:K88),0) -> 11685
B91: Investing Activities
B92: Fixed assets purchased | C92: ='Raw FS'!F58 -> -895 | D92: ='Raw FS'!G58 -> -767 | E92: ='Raw FS'!H58 -> -862 | F92: ='Raw FS'!I58 -> -4163 | G92: ='Raw FS'!J58 -> -1228 | H92: ='Raw FS'!K58 -> -1192 | I92: ='Raw FS'!L58 -> -1477 | J92: ='Raw FS'!M58 -> -1275 | K92: ='Raw FS'!N58 -> -1361
B93: Fixed assets sold | C93: ='Raw FS'!F59 -> 32 | D93: ='Raw FS'!G59 -> 13 | E93: ='Raw FS'!H59 -> 52 | F93: ='Raw FS'!I59 -> 97 | G93: ='Raw FS'!J59 -> 175 | H93: ='Raw FS'!K59 -> 181 | I93: ='Raw FS'!L59 -> 20 | J93: ='Raw FS'!M59 -> 13 | K93: ='Raw FS'!N59 -> 29
B94: Investments purchased | C94: ='Raw FS'!F60 -> -51855 | D94: ='Raw FS'!G60 -> -74365 | E94: ='Raw FS'!H60 -> -36090 | F94: ='Raw FS'!I60 -> -39920 | G94: ='Raw FS'!J60 -> -48522 | H94: ='Raw FS'!K60 -> -22649 | I94: ='Raw FS'!L60 -> -21337 | J94: ='Raw FS'!M60 -> -22957 | K94: ='Raw FS'!N60 -> -25529
B95: Investments sold | C95: ='Raw FS'!F61 -> 52897 | D95: ='Raw FS'!G61 -> 74691 | E95: ='Raw FS'!H61 -> 37690 | F95: ='Raw FS'!I61 -> 38486 | G95: ='Raw FS'!J61 -> 47786 | H95: ='Raw FS'!K61 -> 23462 | I95: ='Raw FS'!L61 -> 19846 | J95: ='Raw FS'!M61 -> 23987 | K95: ='Raw FS'!N61 -> 25117
B96: Interest received | C96: ='Raw FS'!F62 -> 297 | D96: ='Raw FS'!G62 -> 289 | E96: ='Raw FS'!H62 -> 351 | F96: ='Raw FS'!I62 -> 277 | G96: ='Raw FS'!J62 -> 161 | H96: ='Raw FS'!K62 -> 259 | I96: ='Raw FS'!L62 -> 425 | J96: ='Raw FS'!M62 -> 835 | K96: ='Raw FS'!N62 -> 428
B97: Dividends received | C97: ='Raw FS'!F63 -> 0 | D97: ='Raw FS'!G63 -> 1 | E97: ='Raw FS'!H63 -> 1 | F97: ='Raw FS'!I63 -> 1 | G97: ='Raw FS'!J63 -> 1 | H97: ='Raw FS'!K63 -> 2 | I97: ='Raw FS'!L63 -> 3 | J97: ='Raw FS'!M63 -> 0 | K97: ='Raw FS'!N63 -> 5
B98: Redemp n Canc of Shares | C98: ='Raw FS'!F64 -> 73 | D98: ='Raw FS'!G64 -> 0 | E98: ='Raw FS'!H64 -> 0 | F98: ='Raw FS'!I64 -> 0 | G98: ='Raw FS'!J64 -> 0 | H98: ='Raw FS'!K64 -> 0 | I98: ='Raw FS'!L64 -> 0 | J98: ='Raw FS'!M64 -> 0 | K98: ='Raw FS'!N64 -> 298
B99: Acquisition of companies | C99: ='Raw FS'!F65 -> 0 | D99: ='Raw FS'!G65 -> 0 | E99: ='Raw FS'!H65 -> 0 | F99: ='Raw FS'!I65 -> 0 | G99: ='Raw FS'!J65 -> 0 | H99: ='Raw FS'!K65 -> -334 | I99: ='Raw FS'!L65 -> 0 | J99: ='Raw FS'!M65 -> 0 | K99: ='Raw FS'!N65 -> 0
B100: Other investing items | C100: ='Raw FS'!F66 -> -1612 | D100: ='Raw FS'!G66 -> -300 | E100: ='Raw FS'!H66 -> 649 | F100: ='Raw FS'!I66 -> 3994 | G100: ='Raw FS'!J66 -> -101 | H100: ='Raw FS'!K66 -> -1213 | I100: ='Raw FS'!L66 -> -2804 | J100: ='Raw FS'!M66 -> 5870 | K100: ='Raw FS'!N66 -> -2663
B101: Cash Flow From Investing Activities | C101: =IFERROR(SUM(C92:C100),0) -> -1063 | D101: =IFERROR(SUM(D92:D100),0) -> -438 | E101: =IFERROR(SUM(E92:E100),0) -> 1791 | F101: =IFERROR(SUM(F92:F100),0) -> -1228 | G101: =IFERROR(SUM(G92:G100),0) -> -1728 | H101: =IFERROR(SUM(H92:H100),0) -> -1484 | I101: =IFERROR(SUM(I92:I100),0) -> -5324 | J101: =IFERROR(SUM(J92:J100),0) -> 6473 | K101: =IFERROR(SUM(K92:K100),0) -> -3676
B103: Financing Activities
B104: Proceeds from shares | C104: ='Raw FS'!F68 -> 0 | D104: ='Raw FS'!G68 -> 0 | E104: ='Raw FS'!H68 -> 0 | F104: ='Raw FS'!I68 -> 0 | G104: ='Raw FS'!J68 -> 0 | H104: ='Raw FS'!K68 -> 0 | I104: ='Raw FS'!L68 -> 0 | J104: ='Raw FS'!M68 -> 0 | K104: ='Raw FS'!N68 -> 0
B105: Proceeds from borrowings | C105: ='Raw FS'!F69 -> 0 | D105: ='Raw FS'!G69 -> 99 | E105: ='Raw FS'!H69 -> 0 | F105: ='Raw FS'!I69 -> 188 | G105: ='Raw FS'!J69 -> 55 | H105: ='Raw FS'!K69 -> 286 | I105: ='Raw FS'!L69 -> 0 | J105: ='Raw FS'!M69 -> 0 | K105: ='Raw FS'!N69 -> 0
B106: Repayment of borrowings | C106: ='Raw FS'!F70 -> -277 | D106: ='Raw FS'!G70 -> 0 | E106: ='Raw FS'!H70 -> -99 | F106: ='Raw FS'!I70 -> -188 | G106: ='Raw FS'!J70 -> -55 | H106: ='Raw FS'!K70 -> -208 | I106: ='Raw FS'!L70 -> -85 | J106: ='Raw FS'!M70 -> 0 | K106: ='Raw FS'!N70 -> -46
B107: Interest paid fin | C107: ='Raw FS'!F71 -> -6 | D107: ='Raw FS'!G71 -> -7 | E107: ='Raw FS'!H71 -> -90 | F107: ='Raw FS'!I71 -> -92 | G107: ='Raw FS'!J71 -> -82 | H107: ='Raw FS'!K71 -> -88 | I107: ='Raw FS'!L71 -> -110 | J107: ='Raw FS'!M71 -> -130 | K107: ='Raw FS'!N71 -> -133
B108: Dividends paid | C108: ='Raw FS'!F72 -> -3911 | D108: ='Raw FS'!G72 -> -4554 | E108: ='Raw FS'!H72 -> -5196 | F108: ='Raw FS'!I72 -> -8811 | G108: ='Raw FS'!J72 -> -7526 | H108: ='Raw FS'!K72 -> -8474 | I108: ='Raw FS'!L72 -> -9416 | J108: ='Raw FS'!M72 -> -12473 | K108: ='Raw FS'!N72 -> -10124
B109: Financial liabilities | C109: ='Raw FS'!F73 -> 0 | D109: ='Raw FS'!G73 -> 0 | E109: ='Raw FS'!H73 -> -373 | F109: ='Raw FS'!I73 -> -406 | G109: ='Raw FS'!J73 -> -407 | H109: ='Raw FS'!K73 -> -467 | I109: ='Raw FS'!L73 -> -423 | J109: ='Raw FS'!M73 -> -498 | K109: ='Raw FS'!N73 -> -507
B110: Other financing items | C110: ='Raw FS'!F74 -> -781 | D110: ='Raw FS'!G74 -> -928 | E110: ='Raw FS'!H74 -> -1061 | F110: ='Raw FS'!I74 -> 0 | G110: ='Raw FS'!J74 -> 0 | H110: ='Raw FS'!K74 -> -2 | I110: ='Raw FS'!L74 -> 0 | J110: ='Raw FS'!M74 -> 0 | K110: ='Raw FS'!N74 -> 0
B111: Cash Flow From Financing Activities | C111: =IFERROR(SUM(C104:C110),0) -> -4975 | D111: =IFERROR(SUM(D104:D110),0) -> -5390 | E111: =IFERROR(SUM(E104:E110),0) -> -6819 | F111: =IFERROR(SUM(F104:F110),0) -> -9309 | G111: =IFERROR(SUM(G104:G110),0) -> -8015 | H111: =IFERROR(SUM(H104:H110),0) -> -8953 | I111: =IFERROR(SUM(I104:I110),0) -> -10034 | J111: =IFERROR(SUM(J104:J110),0) -> -13101 | K111: =IFERROR(SUM(K104:K110),0) -> -10810
B113: Net Cash Flow | C113: =IFERROR(SUM(C89,C101,C111),0) -> 857 | D113: =IFERROR(SUM(D89,D101,D111),0) -> -370 | E113: =IFERROR(SUM(E89,E101,E111),0) -> 3006 | F113: =IFERROR(SUM(F89,F101,F111),0) -> -1475 | G113: =IFERROR(SUM(G89,G101,G111),0) -> -1695 | H113: =IFERROR(SUM(H89,H101,H111),0) -> -1406 | I113: =IFERROR(SUM(I89,I101,I111),0) -> 1424 | J113: =IFERROR(SUM(J89,J101,J111),0) -> 4470 | K113: =IFERROR(SUM(K89,K101,K111),0) -> -2801

Sheet Ratio Analysis
B2: ="Ratio Analysis - "&'Data Sheet'!B1 -> Ratio Analysis - HINDUSTAN UNILEVER LTD
B3: Years | C3: ='Data Sheet'!C16 -> 43190 | D3: ='Data Sheet'!D16 -> 43555 | E3: ='Data Sheet'!E16 -> 43921 | F3: ='Data Sheet'!F16 -> 44286 | G3: ='Data Sheet'!G16 -> 44651 | H3: ='Data Sheet'!H16 -> 45016 | I3: ='Data Sheet'!I16 -> 45382 | J3: ='Data Sheet'!J16 -> 45747 | K3: ='Data Sheet'!K16 -> 46112 | L3: Trend | M3: Mean | N3: Median
B5: SalesGrowth | D5: =HistoricalFS!D7 -> 0.10592207 | E5: =HistoricalFS!E7 -> 0.012032562 | F5: =HistoricalFS!F7 -> 0.18211296 | G5: =HistoricalFS!G7 -> 0.11520796 | H5: =HistoricalFS!H7 -> 0.15509286 | I5: =HistoricalFS!I7 -> 0.021723341 | J5: =HistoricalFS!J7 -> -0.0091766835 | K5: =HistoricalFS!K7 -> 0.051200104 | M5: =IFERROR(AVERAGE(D5:K5),0) -> 0.079264397 | N5: =IFERROR(MEDIAN(C5:K5),0) -> 0.078561087
B6: EBITDA Growth | D6: =IFERROR((HistoricalFS!D18/HistoricalFS!C18)-1,0) -> 0.18415789 | E6: =IFERROR((HistoricalFS!E18/HistoricalFS!D18)-1,0) -> 0.11047297 | F6: =IFERROR((HistoricalFS!F18/HistoricalFS!E18)-1,0) -> 0.17898793 | G6: =IFERROR((HistoricalFS!G18/HistoricalFS!F18)-1,0) -> 0.10588336 | H6: =IFERROR((HistoricalFS!H18/HistoricalFS!G18)-1,0) -> 0.10033445 | I6: =IFERROR((HistoricalFS!I18/HistoricalFS!H18)-1,0) -> 0.036191419 | J6: =IFERROR((HistoricalFS!J18/HistoricalFS!I18)-1,0) -> 0.0026604816 | K6: =IFERROR((HistoricalFS!K18/HistoricalFS!J18)-1,0) -> 0.023200435 | M6: =IFERROR(AVERAGE(D6:K6),0) -> 0.092736118 | N6: =IFERROR(MEDIAN(C6:K6),0) -> 0.10310891
B7: EBT Growth | D7: =IFERROR((HistoricalFS!D30/HistoricalFS!C30)-1,0) -> 0.19114051 | E7: =IFERROR((HistoricalFS!E30/HistoricalFS!D30)-1,0) -> 0.055421396 | F7: =IFERROR((HistoricalFS!F30/HistoricalFS!E30)-1,0) -> 0.19379934 | G7: =IFERROR((HistoricalFS!G30/HistoricalFS!F30)-1,0) -> 0.11739339 | H7: =IFERROR((HistoricalFS!H30/HistoricalFS!G30)-1,0) -> 0.10600343 | I7: =IFERROR((HistoricalFS!I30/HistoricalFS!H30)-1,0) -> 0.016516749 | J7: =IFERROR((HistoricalFS!J30/HistoricalFS!I30)-1,0) -> -0.0034327561 | K7: =IFERROR((HistoricalFS!K30/HistoricalFS!J30)-1,0) -> 0.017758726 | M7: =IFERROR(AVERAGE(D7:K7),0) -> 0.086825098 | N7: =IFERROR(MEDIAN(C7:K7),0) -> 0.080712413
B8: Net Profit Growth | D8: =IFERROR((HistoricalFS!D36/HistoricalFS!C36)-1,0) -> 0.17726713 | E8: =IFERROR((HistoricalFS!E36/HistoricalFS!D36)-1,0) -> 0.10352039 | F8: =IFERROR((HistoricalFS!F36/HistoricalFS!E36)-1,0) -> 0.23641819 | G8: =IFERROR((HistoricalFS!G36/HistoricalFS!F36)-1,0) -> 0.10780432 | H8: =IFERROR((HistoricalFS!H36/HistoricalFS!G36)-1,0) -> 0.11783697 | I8: =IFERROR((HistoricalFS!I36/HistoricalFS!H36)-1,0) -> -0.023723569 | J8: =IFERROR((HistoricalFS!J36/HistoricalFS!I36)-1,0) -> -0.015742208 | K8: =IFERROR((HistoricalFS!K36/HistoricalFS!J36)-1,0) -> 0.08802061 | M8: =IFERROR(AVERAGE(D8:K8),0) -> 0.098925229 | N8: =IFERROR(MEDIAN(C8:K8),0) -> 0.10566235
B9: Dividend Growth | D9: =IFERROR((HistoricalFS!D44/HistoricalFS!C44)-1,0) -> 0.09989836 | E9: =IFERROR((HistoricalFS!E44/HistoricalFS!D44)-1,0) -> 0.13625865 | F9: =IFERROR((HistoricalFS!F44/HistoricalFS!E44)-1,0) -> 0.76241858 | G9: =IFERROR((HistoricalFS!G44/HistoricalFS!F44)-1,0) -> -0.2265224 | H9: =IFERROR((HistoricalFS!H44/HistoricalFS!G44)-1,0) -> 0.14705882 | I9: =IFERROR((HistoricalFS!I44/HistoricalFS!H44)-1,0) -> 0.076923077 | J9: =IFERROR((HistoricalFS!J44/HistoricalFS!I44)-1,0) -> 0.26190476 | K9: =IFERROR((HistoricalFS!K44/HistoricalFS!J44)-1,0) -> -0.22641509 | M9: =IFERROR(AVERAGE(D9:K9),0) -> 0.12894059 | N9: =IFERROR(MEDIAN(C9:K9),0) -> 0.1180785
B11: Gross Margin | C11: =IFERROR(HistoricalFS!C13,0) -> 0.45663244 | D11: =IFERROR(HistoricalFS!D13,0) -> 0.46372424 | E11: =IFERROR(HistoricalFS!E13,0) -> 0.48183898 | F11: =IFERROR(HistoricalFS!F13,0) -> 0.46200136 | G11: =IFERROR(HistoricalFS!G13,0) -> 0.44579186 | H11: =IFERROR(HistoricalFS!H13,0) -> 0.41596236 | I11: =IFERROR(HistoricalFS!I13,0) -> 0.45632997 | J11: =IFERROR(HistoricalFS!J13,0) -> 0.45344704 | K11: =IFERROR(HistoricalFS!K13,0) -> 0.44726066 | M11: =IFERROR(AVERAGE(C11:K11),0) -> 0.45366543 | N11: =IFERROR(MEDIAN(C11:K11),0) -> 0.45632997
B12: EBITDA Margin | C12: =IFERROR(HistoricalFS!C19,0) -> 0.21097201 | D12: =IFERROR(HistoricalFS!D19,0) -> 0.22589672 | E12: =IFERROR(HistoricalFS!E19,0) -> 0.24786969 | F12: =IFERROR(HistoricalFS!F19,0) -> 0.24721443 | G12: =IFERROR(HistoricalFS!G19,0) -> 0.24514739 | H12: =IFERROR(HistoricalFS!H19,0) -> 0.23352592 | I12: =IFERROR(HistoricalFS!I19,0) -> 0.23683275 | J12: =IFERROR(HistoricalFS!J19,0) -> 0.23966214 | K12: =IFERROR(HistoricalFS!K19,0) -> 0.23327853 | M12: =IFERROR(AVERAGE(C12:K12),0) -> 0.23559995 | N12: =IFERROR(MEDIAN(C12:K12),0) -> 0.23683275
B13: EBIT Margin | C13: =IFERROR(HistoricalFS!C25,0) -> 0.19634266 | D13: =IFERROR(HistoricalFS!D25,0) -> 0.21152379 | E13: =IFERROR(HistoricalFS!E25,0) -> 0.22268306 | F13: =IFERROR(HistoricalFS!F25,0) -> 0.22437697 | G13: =IFERROR(HistoricalFS!G25,0) -> 0.22434504 | H13: =IFERROR(HistoricalFS!H25,0) -> 0.21475735 | I13: =IFERROR(HistoricalFS!I25,0) -> 0.21718689 | J13: =IFERROR(HistoricalFS!J25,0) -> 0.21923102 | K13: =IFERROR(HistoricalFS!K25,0) -> 0.2126016 | M13: =IFERROR(AVERAGE(C13:K13),0) -> 0.21589426 | N13: =IFERROR(MEDIAN(C13:K13),0) -> 0.21718689
B14: EBT Margin | C14: =IFERROR(HistoricalFS!C31,0) -> 0.1956112 | D14: =IFERROR(HistoricalFS!D31,0) -> 0.2106843 | E14: =IFERROR(HistoricalFS!E31,0) -> 0.21971696 | F14: =IFERROR(HistoricalFS!F31,0) -> 0.22188909 | G14: =IFERROR(HistoricalFS!G31,0) -> 0.22232391 | H14: =IFERROR(HistoricalFS!H31,0) -> 0.21287554 | I14: =IFERROR(HistoricalFS!I31,0) -> 0.21179075 | J14: =IFERROR(HistoricalFS!J31,0) -> 0.21301852 | K14: =IFERROR(HistoricalFS!K31,0) -> 0.20624186 | M14: =IFERROR(AVERAGE(C14:K14),0) -> 0.21268357 | N14: =IFERROR(MEDIAN(C14:K14),0) -> 0.21287554
B15: Net Profit Margin | C15: =IFERROR(HistoricalFS!C37,0) -> 0.13712196 | D15: =IFERROR(HistoricalFS!D37,0) -> 0.14596795 | E15: =IFERROR(HistoricalFS!E37,0) -> 0.15916346 | F15: =IFERROR(HistoricalFS!F37,0) -> 0.16647529 | G15: =IFERROR(HistoricalFS!G37,0) -> 0.16537009 | H15: =IFERROR(HistoricalFS!H37,0) -> 0.16003632 | I15: =IFERROR(HistoricalFS!I37,0) -> 0.1529178 | J15: =IFERROR(HistoricalFS!J37,0) -> 0.15190451 | K15: =IFERROR(HistoricalFS!K37,0) -> 0.15722529 | M15: =IFERROR(AVERAGE(C15:K15),0) -> 0.15513141 | N15: =IFERROR(MEDIAN(C15:K15),0) -> 0.15722529
B17: SalesExpenses%Sales | C17: =IFERROR(HistoricalFS!C16,0) -> 0.24566043 | D17: =IFERROR(HistoricalFS!D16,0) -> 0.23782752 | E17: =IFERROR(HistoricalFS!E16,0) -> 0.23396928 | F17: =IFERROR(HistoricalFS!F16,0) -> 0.21478694 | G17: =IFERROR(HistoricalFS!G16,0) -> 0.20064447 | H17: =IFERROR(HistoricalFS!H16,0) -> 0.18243645 | I17: =IFERROR(HistoricalFS!I16,0) -> 0.21949722 | J17: =IFERROR(HistoricalFS!J16,0) -> 0.21378489 | K17: =IFERROR(HistoricalFS!K16,0) -> 0.21398213 | M17: =IFERROR(AVERAGE(C17:K17),0) -> 0.21806548 | N17: =IFERROR(MEDIAN(C17:K17),0) -> 0.21478694
B18: Depreciation%Sales | C18: =IFERROR(HistoricalFS!C22,0) -> 0.014629343 | D18: =IFERROR(HistoricalFS!D22,0) -> 0.014372933 | E18: =IFERROR(HistoricalFS!E22,0) -> 0.025186638 | F18: =IFERROR(HistoricalFS!F22,0) -> 0.022837459 | G18: =IFERROR(HistoricalFS!G22,0) -> 0.020802349 | H18: =IFERROR(HistoricalFS!H22,0) -> 0.01876857 | I18: =IFERROR(HistoricalFS!I22,0) -> 0.019645858 | J18: =IFERROR(HistoricalFS!J22,0) -> 0.020431124 | K18: =IFERROR(HistoricalFS!K22,0) -> 0.020676925 | M18: =IFERROR(AVERAGE(C18:K18),0) -> 0.019705689 | N18: =IFERROR(MEDIAN(C18:K18),0) -> 0.020431124
B19: OperatingIncome%Sales | C19: =C13 -> 0.19634266 | D19: =D13 -> 0.21152379 | E19: =E13 -> 0.22268306 | F19: =F13 -> 0.22437697 | G19: =G13 -> 0.22434504 | H19: =H13 -> 0.21475735 | I19: =I13 -> 0.21718689 | J19: =J13 -> 0.21923102 | K19: =K13 -> 0.2126016 | M19: =IFERROR(AVERAGE(C19:K19),0) -> 0.21589426 | N19: =IFERROR(MEDIAN(C19:K19),0) -> 0.21718689
B21: Return on Capital Employed | C21: =IFERROR(HistoricalFS!C24/SUM(HistoricalFS!C55:C57),0) -> 0.95852218 | D21: =IFERROR(HistoricalFS!D24/SUM(HistoricalFS!D55:D57),0) -> 1.0438112 | E21: =IFERROR(HistoricalFS!E24/SUM(HistoricalFS!E55:E57),0) -> 1.0765585 | F21: =IFERROR(HistoricalFS!F24/SUM(HistoricalFS!F55:F57),0) -> 0.22133658 | G21: =IFERROR(HistoricalFS!G24/SUM(HistoricalFS!G55:G57),0) -> 0.23483155 | H21: =IFERROR(HistoricalFS!H24/SUM(HistoricalFS!H55:H57),0) -> 0.25250859 | I21: =IFERROR(HistoricalFS!I24/SUM(HistoricalFS!I55:I57),0) -> 0.25507571 | J21: =IFERROR(HistoricalFS!J24/SUM(HistoricalFS!J55:J57),0) -> 0.26336925 | K21: =IFERROR(HistoricalFS!K24/SUM(HistoricalFS!K55:K57),0) -> 0.27293546 | M21: =IFERROR(AVERAGE(C21:K21),0) -> 0.50877211 | N21: =IFERROR(MEDIAN(C21:K21),0) -> 0.26336925
B22: Retained Earnings% | C22: =IFERROR(HistoricalFS!C47,0) -> 0.11366434 | D22: =IFERROR(HistoricalFS!D47,0) -> 0.17183688 | E22: =IFERROR(HistoricalFS!E47,0) -> 0.14718888 | F22: =IFERROR(HistoricalFS!F47,0) -> 0 | G22: =IFERROR(HistoricalFS!G47,0) -> 0.078750144 | H22: =IFERROR(HistoricalFS!H47,0) -> 0.054667354 | I22: =IFERROR(HistoricalFS!I47,0) -> 0 | J22: =IFERROR(HistoricalFS!J47,0) -> 0 | K22: =IFERROR(HistoricalFS!K47,0) -> 0.049427782 | M22: =IFERROR(AVERAGE(C22:K22),0) -> 0.06839282 | N22: =IFERROR(MEDIAN(C22:K22),0) -> 0.054667354
B23: Return on Equity% | C23: =IFERROR(HistoricalFS!C36/SUM(HistoricalFS!C55:C56),0) -> 0.66941354 | D23: =IFERROR(HistoricalFS!D36/SUM(HistoricalFS!D55:D56),0) -> 0.72937587 | E23: =IFERROR(HistoricalFS!E36/SUM(HistoricalFS!E55:E56),0) -> 0.76947381 | F23: =IFERROR(HistoricalFS!F36/SUM(HistoricalFS!F55:F56),0) -> 0.16421949 | G23: =IFERROR(HistoricalFS!G36/SUM(HistoricalFS!G55:G56),0) -> 0.17677993 | H23: =IFERROR(HistoricalFS!H36/SUM(HistoricalFS!H55:H56),0) -> 0.19272821 | I23: =IFERROR(HistoricalFS!I36/SUM(HistoricalFS!I55:I56),0) -> 0.18479831 | J23: =IFERROR(HistoricalFS!J36/SUM(HistoricalFS!J55:J56),0) -> 0.18857536 | K23: =IFERROR(HistoricalFS!K36/SUM(HistoricalFS!K55:K56),0) -> 0.20796487 | M23: =IFERROR(AVERAGE(C23:K23),0) -> 0.36481438 | N23: =IFERROR(MEDIAN(C23:K23),0) -> 0.19272821
B24: Self Sustained Growth Rate | C24: =IFERROR(C22*C23,0) -> 0.076088449 | D24: =IFERROR(D22*D23,0) -> 0.12533367 | E24: =IFERROR(E22*E23,0) -> 0.11325799 | F24: =IFERROR(F22*F23,0) -> 0 | G24: =IFERROR(G22*G23,0) -> 0.013921445 | H24: =IFERROR(H22*H23,0) -> 0.010535941 | I24: =IFERROR(I22*I23,0) -> 0 | J24: =IFERROR(J22*J23,0) -> 0 | K24: =IFERROR(K22*K23,0) -> 0.010279242 | M24: =IFERROR(AVERAGE(C24:K24),0) -> 0.038824082 | N24: =IFERROR(MEDIAN(C24:K24),0) -> 0.010535941
B25: Interest Coverage Ratio | C25: =IFERROR(HistoricalFS!C24/HistoricalFS!C27,0) -> 268.42308 | D25: =IFERROR(HistoricalFS!D24/HistoricalFS!D27,0) -> 251.9697 | E25: =IFERROR(HistoricalFS!E24/HistoricalFS!E27,0) -> 75.076271 | F25: =IFERROR(HistoricalFS!F24/HistoricalFS!F27,0) -> 90.188034 | G25: =IFERROR(HistoricalFS!G24/HistoricalFS!G27,0) -> 111 | H25: =IFERROR(HistoricalFS!H24/HistoricalFS!H27,0) -> 114.12281 | I25: =IFERROR(HistoricalFS!I24/HistoricalFS!I27,0) -> 40.248503 | J25: =IFERROR(HistoricalFS!J24/HistoricalFS!J27,0) -> 35.288714 | K25: =IFERROR(HistoricalFS!K24/HistoricalFS!K27,0) -> 33.429268 | M25: =IFERROR(AVERAGE(C25:K25),0) -> 113.30515 | N25: =IFERROR(MEDIAN(C25:K25),0) -> 90.188034
B27: Debtor Turnover Ratio | C27: =IFERROR(HistoricalFS!C6/HistoricalFS!C67,0) -> 27.133588 | D27: =IFERROR(HistoricalFS!D6/HistoricalFS!D67,0) -> 21.646476 | E27: =IFERROR(HistoricalFS!E6/HistoricalFS!E67,0) -> 34.624021 | F27: =IFERROR(HistoricalFS!F6/HistoricalFS!F67,0) -> 26.750853 | G27: =IFERROR(HistoricalFS!G6/HistoricalFS!G67,0) -> 23.455277 | H27: =IFERROR(HistoricalFS!H6/HistoricalFS!H67,0) -> 19.675219 | I27: =IFERROR(HistoricalFS!I6/HistoricalFS!I67,0) -> 20.652653 | J27: =IFERROR(HistoricalFS!J6/HistoricalFS!J67,0) -> 16.058654 | K27: =IFERROR(HistoricalFS!K6/HistoricalFS!K67,0) -> 19.079017 | M27: =IFERROR(AVERAGE(C27:K27),0) -> 23.23064 | N27: =IFERROR(MEDIAN(C27:K27),0) -> 21.646476
B28: Creditor Turnover Ratio | C28: =IFERROR(HistoricalFS!C6/HistoricalFS!C58,0) -> 3.3593233 | D28: =IFERROR(HistoricalFS!D6/HistoricalFS!D58,0) -> 3.6865798 | E28: =IFERROR(HistoricalFS!E6/HistoricalFS!E58,0) -> 3.3363804 | F28: =IFERROR(HistoricalFS!F6/HistoricalFS!F58,0) -> 2.2324124 | G28: =IFERROR(HistoricalFS!G6/HistoricalFS!G58,0) -> 2.5706303 | H28: =IFERROR(HistoricalFS!H6/HistoricalFS!H58,0) -> 2.8106152 | I28: =IFERROR(HistoricalFS!I6/HistoricalFS!I58,0) -> 2.4002792 | J28: =IFERROR(HistoricalFS!J6/HistoricalFS!J58,0) -> 2.1284837 | K28: =IFERROR(HistoricalFS!K6/HistoricalFS!K58,0) -> 2.1838014 | M28: =IFERROR(AVERAGE(C28:K28),0) -> 2.7453895 | N28: =IFERROR(MEDIAN(C28:K28),0) -> 2.5706303
B29: Inventory Turnover | C29: =IFERROR(HistoricalFS!C6/HistoricalFS!C80,0) -> -243.4589 | D29: =IFERROR(HistoricalFS!D6/HistoricalFS!D80,0) -> -201.58974 | E29: =IFERROR(HistoricalFS!E6/HistoricalFS!E80,0) -> -120.19033 | F29: =IFERROR(HistoricalFS!F6/HistoricalFS!F80,0) -> -86.607735 | G29: =IFERROR(HistoricalFS!G6/HistoricalFS!G80,0) -> -69.189974 | H29: =IFERROR(HistoricalFS!H6/HistoricalFS!H80,0) -> -178.70206 | I29: =IFERROR(HistoricalFS!I6/HistoricalFS!I80,0) -> 836.43243 | J29: =IFERROR(HistoricalFS!J6/HistoricalFS!J80,0) -> -105.0137 | K29: =IFERROR(HistoricalFS!K6/HistoricalFS!K80,0) -> -93.16185 | M29: =IFERROR(AVERAGE(C29:K29),0) -> -29.053541 | N29: =IFERROR(MEDIAN(C29:K29),0) -> -105.0137
B30: Fixed Asset Turnover | C30: =IFERROR(HistoricalFS!C6/HistoricalFS!C61,0) -> 7.8500442 | D30: =IFERROR(HistoricalFS!D6/HistoricalFS!D61,0) -> 8.3372216 | E30: =IFERROR(HistoricalFS!E6/HistoricalFS!E61,0) -> 7.2609965 | F30: =IFERROR(HistoricalFS!F6/HistoricalFS!F61,0) -> 0.91417686 | G30: =IFERROR(HistoricalFS!G6/HistoricalFS!G61,0) -> 1.0189031 | H30: =IFERROR(HistoricalFS!H6/HistoricalFS!H61,0) -> 1.1500057 | I30: =IFERROR(HistoricalFS!I6/HistoricalFS!I61,0) -> 1.151682 | J30: =IFERROR(HistoricalFS!J6/HistoricalFS!J61,0) -> 1.1287016 | K30: =IFERROR(HistoricalFS!K6/HistoricalFS!K61,0) -> 1.1225883 | M30: =IFERROR(AVERAGE(C30:K30),0) -> 3.3260355 | N30: =IFERROR(MEDIAN(C30:K30),0) -> 1.1500057
B31: Capital Turnover Ratio | C31: =IFERROR(HistoricalFS!C6/SUM(HistoricalFS!C55:C56),0) -> 4.8818844 | D31: =IFERROR(HistoricalFS!D6/SUM(HistoricalFS!D55:D56),0) -> 4.9968222 | E31: =IFERROR(HistoricalFS!E6/SUM(HistoricalFS!E55:E56),0) -> 4.8344878 | F31: =IFERROR(HistoricalFS!F6/SUM(HistoricalFS!F55:F56),0) -> 0.98644964 | G31: =IFERROR(HistoricalFS!G6/SUM(HistoricalFS!G55:G56),0) -> 1.0689957 | H31: =IFERROR(HistoricalFS!H6/SUM(HistoricalFS!H55:H56),0) -> 1.204278 | I31: =IFERROR(HistoricalFS!I6/SUM(HistoricalFS!I55:I56),0) -> 1.2084814 | J31: =IFERROR(HistoricalFS!J6/SUM(HistoricalFS!J55:J56),0) -> 1.2414072 | K31: =IFERROR(HistoricalFS!K6/SUM(HistoricalFS!K55:K56),0) -> 1.322719 | M31: =IFERROR(AVERAGE(C31:K31),0) -> 2.4161695 | N31: =IFERROR(MEDIAN(C31:K31),0) -> 1.2414072
B33: Debtor Days | C33: =IFERROR(365/C27,0) -> 13.451962 | D33: =IFERROR(365/D27,0) -> 16.861867 | E33: =IFERROR(365/E27,0) -> 10.541814 | F33: =IFERROR(365/F27,0) -> 13.644425 | G33: =IFERROR(365/G27,0) -> 15.56153 | H33: =IFERROR(365/H27,0) -> 18.551255 | I33: =IFERROR(365/I27,0) -> 17.673275 | J33: =IFERROR(365/J27,0) -> 22.729178 | K33: =IFERROR(365/K27,0) -> 19.130964 | M33: =IFERROR(AVERAGE(C33:K33),0) -> 16.460697 | N33: =IFERROR(MEDIAN(C33:K33),0) -> 16.861867
B34: Payable Days | C34: =IFERROR(365/C28,0) -> 108.65283 | D34: =IFERROR(365/D28,0) -> 99.007759 | E34: =IFERROR(365/E28,0) -> 109.39999 | F34: =IFERROR(365/F28,0) -> 163.50026 | G34: =IFERROR(365/G28,0) -> 141.98852 | H34: =IFERROR(365/H28,0) -> 129.86481 | I34: =IFERROR(365/I28,0) -> 152.06564 | J34: =IFERROR(365/J28,0) -> 171.48358 | K34: =IFERROR(365/K28,0) -> 167.13974 | M34: =IFERROR(AVERAGE(C34:K34),0) -> 138.12257 | N34: =IFERROR(MEDIAN(C34:K34),0) -> 141.98852
B35: Inventory Days | C35: =IFERROR(365/C29,0) -> -1.4992263 | D35: =IFERROR(365/D29,0) -> -1.810608 | E35: =IFERROR(365/E29,0) -> -3.0368499 | F35: =IFERROR(365/F29,0) -> -4.2144042 | G35: =IFERROR(365/G29,0) -> -5.2753308 | H35: =IFERROR(365/H29,0) -> -2.0425058 | I35: =IFERROR(365/I29,0) -> 0.43637715 | J35: =IFERROR(365/J29,0) -> -3.475737 | K35: =IFERROR(365/K29,0) -> -3.9179128 | M35: =IFERROR(AVERAGE(C35:K35),0) -> -2.7595775 | N35: =IFERROR(MEDIAN(C35:K35),0) -> -3.0368499
B36: Cash Conversion Cycle (in days) | C36: =SUM(C33,C35)-C34 -> -96.700098 | D36: =SUM(D33,D35)-D34 -> -83.9565 | E36: =SUM(E33,E35)-E34 -> -101.89503 | F36: =SUM(F33,F35)-F34 -> -154.07023 | G36: =SUM(G33,G35)-G34 -> -131.70232 | H36: =SUM(H33,H35)-H34 -> -113.35606 | I36: =SUM(I33,I35)-I34 -> -133.95599 | J36: =SUM(J33,J35)-J34 -> -152.23014 | K36: =SUM(K33,K35)-K34 -> -151.92669 | M36: =IFERROR(AVERAGE(C36:K36),0) -> -124.42145 | N36: =IFERROR(MEDIAN(C36:K36),0) -> -131.70232
B38: CFO/Sales | C38: =IFERROR(HistoricalFS!C89/HistoricalFS!C6,0) -> 0.19397946 | D38: =IFERROR(HistoricalFS!D89/HistoricalFS!D6,0) -> 0.13884508 | E38: =IFERROR(HistoricalFS!E89/HistoricalFS!E6,0) -> 0.20194555 | F38: =IFERROR(HistoricalFS!F89/HistoricalFS!F6,0) -> 0.19269371 | G38: =IFERROR(HistoricalFS!G89/HistoricalFS!G6,0) -> 0.15345308 | H38: =IFERROR(HistoricalFS!H89/HistoricalFS!H6,0) -> 0.1490756 | I38: =IFERROR(HistoricalFS!I89/HistoricalFS!I6,0) -> 0.27113222 | J38: =IFERROR(HistoricalFS!J89/HistoricalFS!J6,0) -> 0.18096139 | K38: =IFERROR(HistoricalFS!K89/HistoricalFS!K6,0) -> 0.18125271 | M38: =IFERROR(AVERAGE(C38:K38),0) -> 0.18481542 | N38: =IFERROR(MEDIAN(C38:K38),0) -> 0.18125271
B39: CFO/Total Assets | C39: =IFERROR(HistoricalFS!C89/HistoricalFS!C72,0) -> 0.386015 | D39: =IFERROR(HistoricalFS!D89/HistoricalFS!D72,0) -> 0.29298406 | E39: =IFERROR(HistoricalFS!E89/HistoricalFS!E72,0) -> 0.39865033 | F39: =IFERROR(HistoricalFS!F89/HistoricalFS!F72,0) -> 0.13183008 | G39: =IFERROR(HistoricalFS!G89/HistoricalFS!G72,0) -> 0.11414631 | H39: =IFERROR(HistoricalFS!H89/HistoricalFS!H72,0) -> 0.12358198 | I39: =IFERROR(HistoricalFS!I89/HistoricalFS!I72,0) -> 0.2138134 | J39: =IFERROR(HistoricalFS!J89/HistoricalFS!J72,0) -> 0.13896297 | K39: =IFERROR(HistoricalFS!K89/HistoricalFS!K72,0) -> 0.14654243 | M39: =IFERROR(AVERAGE(C39:K39),0) -> 0.21628073 | N39: =IFERROR(MEDIAN(C39:K39),0) -> 0.14654243
B40: CFO/Total Debt | C40: =IFERROR(HistoricalFS!C89/HistoricalFS!C57,0) -> 0 | D40: =IFERROR(HistoricalFS!D89/HistoricalFS!D57,0) -> 55.131313 | E40: =IFERROR(HistoricalFS!E89/HistoricalFS!E57,0) -> 0 | F40: =IFERROR(HistoricalFS!F89/HistoricalFS!F57,0) -> 0 | G40: =IFERROR(HistoricalFS!G89/HistoricalFS!G57,0) -> 7.7162033 | H40: =IFERROR(HistoricalFS!H89/HistoricalFS!H57,0) -> 7.4085316 | I40: =IFERROR(HistoricalFS!I89/HistoricalFS!I57,0) -> 11.308625 | J40: =IFERROR(HistoricalFS!J89/HistoricalFS!J57,0) -> 6.7342233 | K40: =IFERROR(HistoricalFS!K89/HistoricalFS!K57,0) -> 7.905954 | M40: =IFERROR(AVERAGE(C40:K40),0) -> 10.689428 | N40: =IFERROR(MEDIAN(C40:K40),0) -> 7.4085316

Sheet Forecasting
B2: ='Data Sheet'!$B$1 &" "& HistoricalFS!B6& " Forecasting" -> HINDUSTAN UNILEVER LTD Sales Forecasting | G2: ='Data Sheet'!$B$1 &" "& HistoricalFS!B18& " Forecasting" -> HINDUSTAN UNILEVER LTD EBITDA Forecasting | L2: ='Data Sheet'!$B$1 &" "& HistoricalFS!B41& "Forecasting" -> HINDUSTAN UNILEVER LTD Earning per Share Forecasting
B3: Year Weight | C3: Year | D3: Sales | E3: Sales Growth | G3: Year Weight | H3: Year | I3: EBITDA | J3: EBITDA Growth | L3: Year Weight | M3: Year | N3: EPS | O3: EPS Growth
B4: 1 | C4: =IFERROR('Data Sheet'!$C$16,0) -> 43190 | D4: {=TRANSPOSE('Data Sheet'!C17:K17)} -> 35545 | G4: 1 | H4: =IFERROR(C4,0) -> 43190 | I4: {=TRANSPOSE(HistoricalFS!C18:L18)} -> 7499 | L4: 1 | M4: =IFERROR(H4,0) -> 43190 | N4: {=TRANSPOSE(HistoricalFS!C41:L41)} -> 22.519983
B5: =B4+1 -> 2 | C5: =IFERROR(C4+365,0) -> 43555 | D5: 39310 | E5: =D5/D4-1 -> 0.10592207 | G5: =G4+1 -> 2 | H5: =IFERROR(C5,0) -> 43555 | I5: 8880 | J5: =I5/I4-1 -> 0.18415789 | L5: =L4+1 -> 2 | M5: =IFERROR(H5,0) -> 43555 | N5: 26.509587 | O5: =IFERROR(N5/N4-1,0) -> 0.17715835
B6: =B5+1 -> 3 | C6: =IFERROR(C5+365,0) -> 43920 | D6: 39783 | E6: =D6/D5-1 -> 0.012032562 | G6: =G5+1 -> 3 | H6: =IFERROR(C6,0) -> 43920 | I6: 9861 | J6: =I6/I5-1 -> 0.11047297 | L6: =L5+1 -> 3 | M6: =IFERROR(H6,0) -> 43920 | N6: 29.251166 | O6: =IFERROR(N6/N5-1,0) -> 0.10341843
B7: =B6+1 -> 4 | C7: =IFERROR(C6+365,0) -> 44285 | D7: 47028 | E7: =D7/D6-1 -> 0.18211296 | G7: =G6+1 -> 4 | H7: =IFERROR(C7,0) -> 44285 | I7: 11626 | J7: =I7/I6-1 -> 0.17898793 | L7: =L6+1 -> 4 | M7: =IFERROR(H7,0) -> 44285 | N7: 36.165004 | O7: =IFERROR(N7/N6-1,0) -> 0.23636108
B8: =B7+1 -> 5 | C8: =IFERROR(C7+365,0) -> 44650 | D8: 52446 | E8: =D8/D7-1 -> 0.11520796 | G8: =G7+1 -> 5 | H8: =IFERROR(C8,0) -> 44650 | I8: 12857 | J8: =I8/I7-1 -> 0.10588336 | L8: =L7+1 -> 5 | M8: =IFERROR(H8,0) -> 44650 | N8: 36.912666 | O8: =IFERROR(N8/N7-1,0) -> 0.020673641
B9: =B8+1 -> 6 | C9: =IFERROR(C8+365,0) -> 45015 | D9: 60580 | E9: =D9/D8-1 -> 0.15509286 | G9: =G8+1 -> 6 | H9: =IFERROR(C9,0) -> 45015 | I9: 14147 | J9: =I9/I8-1 -> 0.10033445 | L9: =L8+1 -> 6 | M9: =IFERROR(H9,0) -> 45015 | N9: 41.262343 | O9: =IFERROR(N9/N8-1,0) -> 0.11783697
B10: =B9+1 -> 7 | C10: =IFERROR(C9+365,0) -> 45380 | D10: 61896 | E10: =D10/D9-1 -> 0.021723341 | G10: =G9+1 -> 7 | H10: =IFERROR(C10,0) -> 45380 | I10: 14659 | J10: =I10/I9-1 -> 0.036191419 | L10: =L9+1 -> 7 | M10: =IFERROR(H10,0) -> 45380 | N10: 40.283453 | O10: =IFERROR(N10/N9-1,0) -> -0.023723569
B11: =B10+1 -> 8 | C11: =IFERROR(C10+365,0) -> 45745 | D11: 61328 | E11: =D11/D10-1 -> -0.0091766835 | G11: =G10+1 -> 8 | H11: =IFERROR(C11,0) -> 45745 | I11: 14698 | J11: =I11/I10-1 -> 0.0026604816 | L11: =L10+1 -> 8 | M11: =IFERROR(H11,0) -> 45745 | N11: 39.649302 | O11: =IFERROR(N11/N10-1,0) -> -0.015742208
B12: =B11+1 -> 9 | C12: =IFERROR(C11+365,0) -> 46110 | D12: 64468 | E12: =D12/D11-1 -> 0.051200104 | G12: =G11+1 -> 9 | H12: =IFERROR(C12,0) -> 46110 | I12: 15039 | J12: =I12/I11-1 -> 0.023200435 | L12: =L11+1 -> 9 | M12: =IFERROR(H12,0) -> 46110 | N12: 43.139258 | O12: =IFERROR(N12/N11-1,0) -> 0.08802061
B13: =B12+1 -> 10 | C13: =IFERROR(C12+365,0) -> 46475 | D13: =FORECAST(B13,$D$4:$D$12,$B$4:$B$12) -> 71336.333 | E13: =D13/D12-1 -> 0.10653864 | G13: =G12+1 -> 10 | H13: =IFERROR(C13,0) -> 46475 | I13: =FORECAST(G13,$I$4:$I$12,$G$4:$G$12) -> 17118.25 | J13: =I13/I12-1 -> 0.1382572 | L13: =L12+1 -> 10 | M13: =IFERROR(H13,0) -> 46475 | N13: =FORECAST(L13,$N$4:$N$12,$L$4:$L$12) -> 47.498486 | O13: =IFERROR(N13/N12-1,0) -> 0.10105015
B14: =B13+1 -> 11 | C14: =IFERROR(C13+365,0) -> 46840 | D14: =FORECAST(B14,$D$4:$D$12,$B$4:$B$12) -> 75328.4 | E14: =D14/D13-1 -> 0.055961198 | G14: =G13+1 -> 11 | H14: =IFERROR(C14,0) -> 46840 | I14: =FORECAST(G14,$I$4:$I$12,$G$4:$G$12) -> 18113.767 | J14: =I14/I13-1 -> 0.058155283 | L14: =L13+1 -> 11 | M14: =IFERROR(H14,0) -> 46840 | N14: =FORECAST(L14,$N$4:$N$12,$L$4:$L$12) -> 49.982789 | O14: =IFERROR(N14/N13-1,0) -> 0.052302774
B15: =B14+1 -> 12 | C15: =IFERROR(C14+365,0) -> 47205 | D15: =FORECAST(B15,$D$4:$D$12,$B$4:$B$12) -> 79320.467 | E15: =D15/D14-1 -> 0.052995506 | G15: =G14+1 -> 12 | H15: =IFERROR(C15,0) -> 47205 | I15: =FORECAST(G15,$I$4:$I$12,$G$4:$G$12) -> 19109.283 | J15: =I15/I14-1 -> 0.054959119 | L15: =L14+1 -> 12 | M15: =IFERROR(H15,0) -> 47205 | N15: =FORECAST(L15,$N$4:$N$12,$L$4:$L$12) -> 52.467091 | O15: =IFERROR(N15/N14-1,0) -> 0.049703161
B16: =B15+1 -> 13 | C16: =IFERROR(C15+365,0) -> 47570 | D16: =FORECAST(B16,$D$4:$D$12,$B$4:$B$12) -> 83312.533 | E16: =D16/D15-1 -> 0.050328331 | G16: =G15+1 -> 13 | H16: =IFERROR(C16,0) -> 47570 | I16: =FORECAST(G16,$I$4:$I$12,$G$4:$G$12) -> 20104.8 | J16: =I16/I15-1 -> 0.052095971 | L16: =L15+1 -> 13 | M16: =IFERROR(H16,0) -> 47570 | N16: =FORECAST(L16,$N$4:$N$12,$L$4:$L$12) -> 54.951394 | O16: =IFERROR(N16/N15-1,0) -> 0.047349729
B17: =B16+1 -> 14 | C17: =IFERROR(C16+365,0) -> 47935 | D17: =FORECAST(B17,$D$4:$D$12,$B$4:$B$12) -> 87304.6 | E17: =D17/D16-1 -> 0.04791676 | G17: =G16+1 -> 14 | H17: =IFERROR(C17,0) -> 47935 | I17: =FORECAST(G17,$I$4:$I$12,$G$4:$G$12) -> 21100.317 | J17: =I17/I16-1 -> 0.049516368 | L17: =L16+1 -> 14 | M17: =IFERROR(H17,0) -> 47935 | N17: =FORECAST(L17,$N$4:$N$12,$L$4:$L$12) -> 57.435697 | O17: =IFERROR(N17/N16-1,0) -> 0.045209091

Sheet Data Room>

Sheet Data Sheet
A1: COMPANY NAME | B1: HINDUSTAN UNILEVER LTD | E1: =IF(B2<>B3, "A NEW VERSION OF THE WORKSHEET IS AVAILABLE", "")
A2: LATEST VERSION | B2: 2.1 | E2: PLEASE DO NOT MAKE ANY CHANGES TO THIS SHEET
A3: CURRENT VERSION | B3: 2.1
A5: META
A6: Number of shares | B6: =IF(B9>0, B9/B8, 0) -> 234.95912
A7: Face Value | B7: 1
A8: Current Price | B8: 2164.2
A9: Market Capitalization | B9: 508498.52
A15: PROFIT & LOSS
A16: Report Date | B16: 42825 | C16: 43190 | D16: 43555 | E16: 43921 | F16: 44286 | G16: 44651 | H16: 45016 | I16: 45382 | J16: 45747 | K16: 46112
A17: Sales | B17: 33162 | C17: 35545 | D17: 39310 | E17: 39783 | F17: 47028 | G17: 52446 | H17: 60580 | I17: 61896 | J17: 61328 | K17: 64468
A18: Raw Material Cost | B18: 13606 | C18: 14233 | D18: 15845 | E18: 15697 | F18: 20141 | G18: 22871 | H18: 28427 | I18: 26822 | J18: 26602 | K18: 29158
A19: Change in Inventory | B19: -144 | C19: 72 | D19: -12 | E19: 108 | F19: 405 | G19: 22 | H19: 75 | I19: 11 | J19: 125 | K19: 429
A20: Power and Fuel | B20: 295 | C20: 295 | D20: 308 | E20: 299 | F20: 339 | G20: 318 | H20: 384 | I20: 446 | J20: 403 | K20: 426
A21: Other Mfr. Exp | B21: 2887 | C21: 2998 | D21: 3041 | E21: 2906 | F21: 2868 | G21: 3354 | H21: 3791 | I21: 3385 | J21: 3687 | K21: 3304
A22: Employee Cost | B22: 1743 | C22: 1860 | D22: 1875 | E22: 1820 | F22: 2358 | G22: 2545 | H22: 2854 | I22: 3009 | J22: 2952 | K22: 3175
A23: Selling and admin | B23: 6689 | C23: 7252 | D23: 7796 | E23: 7620 | F23: 7906 | G23: 8164 | H23: 8785 | I23: 10780 | J23: 10145 | K23: 10744
A24: Other Expenses | B24: 1470 | C24: 1480 | D24: 1553 | E24: 1688 | F24: 2195 | G24: 2359 | H24: 2267 | I24: 2806 | J24: 2966 | K24: 3051
A25: Other Income | B25: 606 | C25: 353 | D25: 322 | E25: 424 | F25: 170 | G25: 219 | H25: 448 | I25: 817 | J25: 1355 | K25: 4923
A26: Depreciation | B26: 432 | C26: 520 | D26: 565 | E26: 1002 | F26: 1074 | G26: 1091 | H26: 1137 | I26: 1216 | J26: 1253 | K26: 1333
A27: Interest | B27: 35 | C27: 26 | D27: 33 | E27: 118 | F27: 117 | G27: 106 | H27: 114 | I27: 334 | J27: 381 | K27: 410
... A31: Dividend Amount | B31: 3672 | C31: 4320 | D31: 4752 | E31: 5400 | F31: 9517.5 | G31: 7990 | H31: 9165 | I31: 9870 | J31: 12455 | K31: 9635
A40: Quarters
A41: Report Date | B41: 45291 | C41: 45382 | D41: 45473 | E41: 45565 | F41: 45657 | G41: 45747 | H41: 45838 | I41: 45930 | J41: 46022 | K41: 46112
A42: Sales | B42: 15567 | C42: 15210 | D42: 15707 | E42: 15926 | F42: 15556 | G42: 15190 | H42: 16514 | I42: 15919 | J42: 16441 | K42: 16351
A43: Expenses | B43: 11902 | C43: 11675 | D43: 11965 | E43: 12139 | F43: 11867 | G43: 11572 | H43: 12797 | I43: 12137 | J43: 12660 | K43: 12514
A44: Other Income | B44: 184 | C44: 309 | D44: 209 | E44: 203 | F44: 733 | G44: 149 | H44: 74 | I44: 269 | J44: 4048 | K44: 503
A45: Depreciation | B45: 313 | C45: 320 | D45: 329 | E45: 338 | F45: 318 | G45: 318 | H45: 361 | I45: 322 | J45: 337 | K45: 348
A46: Interest | B46: 91 | C46: 105 | D46: 93 | E46: 110 | F46: 109 | G46: 77 | H46: 127 | I46: 124 | J46: 88 | K46: 76
A47: Profit before tax | B47: 3445 | C47: 3419 | D47: 3529 | E47: 3542 | F47: 3995 | G47: 3372 | H47: 3303 | I47: 3605 | J47: 7404 | K47: 3916
A48: Tax | B48: 937 | C48: 858 | D48: 917 | E48: 947 | F48: 1006 | G48: 897 | H48: 535 | I48: 911 | J48: 801 | K48: 922
A49: Net profit | B49: 2509 | C49: 2558 | D49: 2610 | E49: 2591 | F49: 2984 | G49: 2464 | H49: 2756 | I49: 2685 | J49: 6607 | K49: 2992
A50: Operating Profit | B50: 3665 | C50: 3535 | D50: 3742 | E50: 3787 | F50: 3689 | G50: 3618 | H50: 3717 | I50: 3782 | J50: 3781 | K50: 3837
A55: BALANCE SHEET
A56: Report Date | B56: 42825 | C56: 43190 | D56: 43555 | E56: 43921 | F56: 44286 | G56: 44651 | H56: 45016 | I56: 45382 | J56: 45747 | K56: 46112
A57: Equity Share Capital | B57: 216 | C57: 216 | D57: 216 | E57: 216 | F57: 235 | G57: 235 | H57: 235 | I57: 235 | J57: 235 | K57: 235
A58: Reserves | B58: 6528 | C58: 7065 | D58: 7651 | E58: 8013 | F58: 47439 | G58: 48826 | H58: 50069 | I58: 50983 | J58: 49167 | K58: 48504
A59: Borrowings | B59: 277 | D59: 99 | G59: 1043 | H59: 1219 | I59: 1484 | J59: 1648 | K59: 1478
A60: Other Liabilities | B60: 8685 | C60: 10581 | D60: 10663 | E60: 11924 | F60: 21066 | G60: 20402 | H60: 21554 | I60: 25787 | J60: 28813 | K60: 29521
A61: Total | B61: 15706 | C61: 17862 | D61: 18629 | E61: 20153 | F61: 68740 | G61: 70506 | H61: 73077 | I61: 78489 | J61: 79863 | K61: 79738
A62: Net Block | B62: 4419 | C62: 4528 | D62: 4715 | E62: 5479 | F62: 51443 | G62: 51473 | H62: 52678 | I62: 53744 | J62: 54335 | K62: 57428
A63: Capital Work in Progress | B63: 229 | C63: 461 | D63: 406 | E63: 597 | F63: 745 | G63: 1313 | H63: 1132 | I63: 1025 | J63: 1009 | K63: 880
A64: Investments | B64: 3794 | C64: 2873 | D64: 2716 | E64: 1255 | F64: 2709 | G64: 3521 | H64: 2882 | I64: 4625 | J64: 3810 | K64: 4359
A65: Other Assets | B65: 7264 | C65: 10000 | D65: 10792 | E65: 12822 | F65: 13843 | G65: 14199 | H65: 16385 | I65: 19095 | J65: 20709 | K65: 17071
A66: Total | B66: 15706 | C66: 17862 | D66: 18629 | E66: 20153 | F66: 68740 | G66: 70506 | H66: 73077 | I66: 78489 | J66: 79863 | K66: 79738
A67: Receivables | B67: 1085 | C67: 1310 | D67: 1816 | E67: 1149 | F67: 1758 | G67: 2236 | H67: 3079 | I67: 2997 | J67: 3819 | K67: 3379
A68: Inventory | B68: 2541 | C68: 2513 | D68: 2574 | E68: 2767 | F68: 3579 | G68: 4096 | H68: 4251 | I68: 4022 | J68: 4415 | K68: 4789
A69: Cash & Bank | B69: 1828 | C69: 3485 | D69: 3757 | E69: 5113 | F69: 4471 | G69: 3846 | H69: 4678 | I69: 7559 | J69: 7554 | K69: 3248
A70: No. of Equity Shares | B70: 2164349639 | C70: 2164528777 | D70: 2164704405 | E70: 2164704405 | F70: 2349567819 | G70: 2349591262 | H70: 2349591262 | I70: 2349591262 | J70: 2349591262 | K70: 2349591262
A71: New Bonus Shares
A72: Face value | B72: 1 | C72: 1 | D72: 1 | E72: 1 | F72: 1 | G72: 1 | H72: 1 | I72: 1 | J72: 1 | K72: 1
A80: CASH FLOW:
A81: Report Date | B81: 42825 | C81: 43190 | D81: 43555 | E81: 43921 | F81: 44286 | G81: 44651 | H81: 45016 | I81: 45382 | J81: 45747 | K81: 46112
A82: Cash from Operating Activity | B82: 5185 | C82: 6059 | D82: 5800 | E82: 7623 | F82: 9163 | G82: 9048 | H82: 9991 | I82: 15469 | J82: 11886 | K82: 10999
A83: Cash from Investing Activity | B83: -1173 | C83: -1063 | D83: -438 | E83: 1791 | F83: -1228 | G83: -1728 | H83: -1484 | I83: -5324 | J83: 6473 | K83: -3676
A84: Cash from Financing Activity | B84: -4214 | C84: -4975 | D84: -5390 | E84: -6819 | F84: -9309 | G84: -8015 | H84: -8953 | I84: -10034 | J84: -13101 | K84: -10810
A85: Net Cash Flow | B85: -202 | C85: 21 | D85: -28 | E85: 2595 | F85: -1374 | G85: -695 | H85: -446 | I85: 111 | J85: 5258 | K85: -3487
A90: PRICE: | B90: 872.61 | C90: 1276.11 | D90: 1633.53 | E90: 2199.83 | F90: 2327.12 | G90: 1960.7 | H90: 2450.44 | I90: 2167.14 | J90: 2161.88 | K90: 2055.2
A92: DERIVED:
A93: Adjusted Equity Shares in Cr | B93: 216.43 | C93: 216.45 | D93: 216.47 | E93: 216.48 | F93: 234.96 | G93: 234.96 | H93: 234.96 | I93: 234.96 | J93: 234.96 | K93: 234.96

Sheet Raw FS
B2: Particulars | C2: 42064 | D2: =C2+366 -> 42430 | E2: =D2+366 -> 42796 | F2: =E2+366 -> 43162 | G2: =F2+366 -> 43528 | H2: =G2+366 -> 43894 | I2: =H2+366 -> 44260 | J2: =I2+366 -> 44626 | K2: =J2+366 -> 44992 | ... N2: =M2+366 -> 46090
B4: Equity Capital | C4: 216 | D4: 216 | E4: 216 | F4: 216 | G4: 216 | H4: 216 | I4: 235 | J4: 235 | K4: 235 | L4: 235 | M4: 235 | N4: 235
B5: Reserves | C5: 3811 | D5: 6357 | E5: 6528 | F5: 7065 | G5: 7651 | H5: 8013 | I5: 47439 | J5: 48826 | K5: 50069 | L5: 50983 | M5: 49167 | N5: 48504
B6: Borrowings -
B7: Long term Borrowings | C7: 7 | D7: 0 | E7: 0 | F7: 0 | G7: 0 | H7: 0 | I7: 0 | J7: 0 | K7: 0 | L7: 0 | M7: 0 | N7: 0
B8: Short term Borrowings | C8: 36 | D8: 177 | E8: 277 | F8: 0 | G8: 99 | H8: 0 | I8: 0 | J8: 0 | K8: 98 | L8: 13 | M8: 1 | N8: 0
B9: Lease Liabilities | C9: 0 | D9: 0 | E9: 0 | F9: 0 | G9: 0 | H9: 0 | I9: 0 | J9: 1043 | K9: 1121 | L9: 1471 | M9: 1647 | N9: 1478
B10: Other Liabilities -
B11: Non controlling int | C11: 25 | D11: 20 | E11: 22 | F11: 20 | G11: 18 | H11: 17 | I11: 20 | J11: 26 | K11: 218 | L11: 205 | M11: 207 | N11: 269
B12: Trade Payables | C12: 5506 | D12: 5685 | E12: 6186 | F12: 7170 | G12: 7206 | H12: 7535 | I12: 8802 | J12: 9068 | K12: 9574 | L12: 10486 | M12: 11315 | N12: 13325
B13: Advance from Customers | C13: 45 | D13: 45 | E13: 78 | F13: 62 | G13: 43 | H13: 158 | I13: 96 | J13: 119 | K13: 98 | L13: 91 | M13: 0 | N13: 0
B14: Other liability items | C14: 4783 | D14: 2293 | E14: 2399 | F14: 3329 | G14: 3396 | H14: 4214 | I14: 12148 | J14: 11189 | K14: 11664 | L14: 15005 | M14: 17291 | N14: 15927
B15: Total Liabilities | C15: 14430 | D15: 14793 | E15: 15706 | F15: 17862 | G15: 18629 | H15: 20153 | I15: 68740 | J15: 70506 | K15: 73077 | L15: 78489 | M15: 79863 | N15: 79738
B17: Fixed Assets -
B18: Land | C18: 102 | D18: 88 | E18: 89 | F18: 87 | G18: 86 | H18: 59 | I18: 477 | J18: 477 | K18: 609 | L18: 633 | M18: 628 | N18: 636
B19: Building | C19: 1173 | D19: 931 | E19: 1210 | F19: 1343 | G19: 1527 | H19: 2044 | I19: 2602 | J19: 2788 | K19: 3101 | L19: 3590 | M19: 3833 | N19: 4067
B20: Plant Machinery | C20: 3481 | D20: 2370 | E20: 3270 | F20: 3691 | G20: 4092 | H20: 5001 | I20: 6097 | J20: 6566 | K20: 7612 | L20: 8946 | M20: 9900 | N20: 9296
B21: Equipments | C21: 106 | D21: 41 | E21: 62 | F21: 74 | G21: 95 | H21: 139 | I21: 175 | J21: 181 | K21: 185 | L21: 206 | M21: 245 | N21: 286
B22: Furniture n fittings | C22: 108 | D22: 61 | E22: 66 | F22: 76 | G22: 88 | H22: 154 | I22: 156 | J22: 152 | K22: 161 | L22: 165 | M22: 174 | N22: 220
B23: Railway sidings | C23: 0 | D23: 0 | E23: 0 | F23: 0 | G23: 0 | H23: 0 | I23: 0 | J23: 0 | K23: 0 | L23: 0 | M23: 0 | N23: 0
B24: Vehicles | C24: 1 | D24: 0 | E24: 0 | F24: 0 | G24: 0 | H24: 0 | I24: 0 | J24: 0 | K24: 33 | L24: 39 | M24: 102 | N24: 103
B25: Intangible Assets | C25: 247 | D25: 85 | E25: 455 | F25: 455 | G25: 511 | H25: 511 | I25: 45262 | J25: 45262 | K25: 45692 | L25: 45692 | M25: 45692 | N25: 49195
B26: Other fixed assets | C26: 193 | D26: 19 | E26: 19 | F26: 26 | G26: 60 | H26: 71 | I26: 155 | J26: 152 | K26: 171 | L26: 180 | M26: 190 | N26: 210
B27: Gross Block | C27: 5412 | D27: 3595 | E27: 5171 | F27: 5752 | G27: 6459 | H27: 7979 | I27: 54924 | J27: 55578 | K27: 57564 | L27: 59451 | M27: 60764 | N27: 64013
B28: Accumulated Depreciation | C28: 2591 | D28: 337 | E28: 752 | F28: 1224 | G28: 1744 | H28: 2500 | I28: 3481 | J28: 4105 | K28: 4886 | L28: 5707 | M28: 6429 | N28: 6585
B29: Net Block | C29: =C27-C28 -> 2821 | D29: =D27-D28 -> 3258 | E29: =E27-E28 -> 4419 | F29: =F27-F28 -> 4528 | G29: =G27-G28 -> 4715 | H29: =H27-H28 -> 5479 | I29: =I27-I28 -> 51443 | J29: =J27-J28 -> 51473 | ... N29: =N27-N28 -> 57428
B31: CWIP | C31: 516 | D31: 408 | E31: 229 | F31: 461 | G31: 406 | H31: 597 | I31: 745 | J31: 1313 | K31: 1132 | L31: 1025 | M31: 1009 | N31: 880
B32: Investments | C32: 3025 | D32: 2592 | E32: 3794 | F32: 2873 | G32: 2716 | H32: 1255 | I32: 2709 | J32: 3521 | K32: 2882 | L32: 4625 | M32: 3810 | N32: 4359
B34: Other Assets -
B35: Inventories | C35: 2849 | D35: 2726 | E35: 2541 | F35: 2513 | G35: 2574 | H35: 2767 | I35: 3579 | J35: 4096 | K35: 4251 | L35: 4022 | M35: 4415 | N35: 4789
B36: Trade receivables + | C36: 1010 | D36: 1264 | E36: 1085 | F36: 1310 | G36: 1816 | H36: 1149 | I36: 1758 | J36: 2236 | K36: 3079 | L36: 2997 | M36: 3819 | N36: 3379
B37: Cash Equivalents | C37: 2689 | D37: 3009 | E37: 1828 | F37: 3485 | G37: 3757 | H37: 5113 | I37: 4471 | J37: 3846 | K37: 4678 | L37: 7559 | M37: 7554 | N37: 3248
B38: Loans n Advances | C38: 0 | D38: 0 | E38: 71 | F38: 40 | G38: 26 | H38: 19 | I38: 78 | J38: 170 | K38: 188 | L38: 172 | M38: 619 | N38: 1024
B39: Other asset items | C39: 1519 | D39: 1536 | E39: 1739 | F39: 2652 | G39: 2619 | H39: 3774 | I39: 3957 | J39: 3851 | K39: 4189 | L39: 4345 | M39: 4302 | N39: 4631
B40: Total Assets | C40: 14430 | D40: 14793 | E40: 15706 | F40: 17862 | G40: 18629 | H40: 20153 | I40: 68740 | J40: 70506 | K40: 73077 | L40: 78489 | M40: 79863 | N40: 79738
B45: Cash from Operating Activity - | C45: 3292 | D45: 4171 | E45: 5185 | F45: 6059 | G45: 5800 | H45: 7623 | I45: 9163 | J45: 9048 | K45: 9991 | L45: 15469 | M45: 11886 | N45: 10999
B46: Profit from operations | C46: 5510 | D46: 6025 | E46: 6512 | F46: 7485 | G46: 8909 | H46: 9723 | I46: 11672 | J46: 12829 | K46: 14089 | L46: 14537 | M46: 14942 | N46: 15153
B47: Receivables | C47: 3 | D47: -257 | E47: 173 | F47: 0 | G47: 0 | H47: 0 | I47: 0 | J47: 0 | K47: 0 | L47: 0 | M47: 0 | N47: 0
B48: Inventory | C48: 91 | D48: 89 | E48: 37 | F48: -146 | G48: -195 | H48: -331 | I48: -543 | J48: -758 | K48: -339 | L48: 74 | M48: -584 | N48: -692
B49: Payables | C49: -327 | D49: 164 | E49: 501 | F49: 0 | G49: 0 | H49: 0 | I49: 0 | J49: 0 | K49: 0 | L49: 0 | M49: 0 | N49: 0
B50: Loans Advances | C50: -148 | D50: 0 | E50: 0 | F50: 0 | G50: 0 | H50: 0 | I50: 0 | J50: 0 | K50: 0 | L50: 0 | M50: 0 | N50: 0
... B77: CFO/OP | C77: 0.95 | D77: 1 | E77: 1.11 | F77: 1.11 | G77: 0.96 | H77: 1.03 | I77: 1 | J77: 0.92 | K77: 0.93 | L77: 1.08 | M77: 0.96 | N77: 1.05
